[
  {
    "sn": {"": "1"},
    "GRE": "337",
    "TOEFL": "118",
    "univRating": "4",
    "SOP": "4.5",
    "LOR": "4.5",
    "CGPA": "9.65",
    "Research": "1",
    "admit": "0.92"
  },
  {
    "sn": {"": "2"},
    "GRE": "324",
    "TOEFL": "107",
    "univRating": "4",
    "SOP": "4",
    "LOR": "4.5",
    "CGPA": "8.87",
    "Research": "1",
    "admit": "0.76"
  },
  {
    "sn": {"": "3"},
    "GRE": "316",
    "TOEFL": "104",
    "univRating": "3",
    "SOP": "3",
    "LOR": "3.5",
    "CGPA": "8",
    "Research": "1",
    "admit": "0.72"
  },
  {
    "sn": {"": "4"},
    "GRE": "322",
    "TOEFL": "110",
    "univRating": "3",
    "SOP": "3.5",
    "LOR": "2.5",
    "CGPA": "8.67",
    "Research": "1",
    "admit": "0.8"
  },
  {
    "sn": {"": "5"},
    "GRE": "314",
    "TOEFL": "103",
    "univRating": "2",
    "SOP": "2",
    "LOR": "3",
    "CGPA": "8.21",
    "Research": "0",
    "admit": "0.65"
  },
  {
    "sn": {"": "6"},
    "GRE": "330",
    "TOEFL": "115",
    "univRating": "5",
    "SOP": "4.5",
    "LOR": "3",
    "CGPA": "9.34",
    "Research": "1",
    "admit": "0.9"
  },
  {
    "sn": {"": "7"},
    "GRE": "321",
    "TOEFL": "109",
    "univRating": "3",
    "SOP": "3",
    "LOR": "4",
    "CGPA": "8.2",
    "Research": "1",
    "admit": "0.75"
  },
  {
    "sn": {"": "8"},
    "GRE": "308",
    "TOEFL": "101",
    "univRating": "2",
    "SOP": "3",
    "LOR": "4",
    "CGPA": "7.9",
    "Research": "0",
    "admit": "0.68"
  },
  {
    "sn": {"": "9"},
    "GRE": "302",
    "TOEFL": "102",
    "univRating": "1",
    "SOP": "2",
    "LOR": "1.5",
    "CGPA": "8",
    "Research": "0",
    "admit": "0.5"
  },
  {
    "sn": {"": "10"},
    "GRE": "323",
    "TOEFL": "108",
    "univRating": "3",
    "SOP": "3.5",
    "LOR": "3",
    "CGPA": "8.6",
    "Research": "0",
    "admit": "0.45"
  },
  {
    "sn": {"": "11"},
    "GRE": "325",
    "TOEFL": "106",
    "univRating": "3",
    "SOP": "3.5",
    "LOR": "4",
    "CGPA": "8.4",
    "Research": "1",
    "admit": "0.52"
  },
  {
    "sn": {"": "12"},
    "GRE": "327",
    "TOEFL": "111",
    "univRating": "4",
    "SOP": "4",
    "LOR": "4.5",
    "CGPA": "9",
    "Research": "1",
    "admit": "0.84"
  },
  {
    "sn": {"": "13"},
    "GRE": "328",
    "TOEFL": "112",
    "univRating": "4",
    "SOP": "4",
    "LOR": "4.5",
    "CGPA": "9.1",
    "Research": "1",
    "admit": "0.78"
  },
  {
    "sn": {"": "14"},
    "GRE": "307",
    "TOEFL": "109",
    "univRating": "3",
    "SOP": "4",
    "LOR": "3",
    "CGPA": "8",
    "Research": "1",
    "admit": "0.62"
  },
  {
    "sn": {"": "15"},
    "GRE": "311",
    "TOEFL": "104",
    "univRating": "3",
    "SOP": "3.5",
    "LOR": "2",
    "CGPA": "8.2",
    "Research": "1",
    "admit": "0.61"
  },
  {
    "sn": {"": "16"},
    "GRE": "314",
    "TOEFL": "105",
    "univRating": "3",
    "SOP": "3.5",
    "LOR": "2.5",
    "CGPA": "8.3",
    "Research": "0",
    "admit": "0.54"
  },
  {
    "sn": {"": "17"},
    "GRE": "317",
    "TOEFL": "107",
    "univRating": "3",
    "SOP": "4",
    "LOR": "3",
    "CGPA": "8.7",
    "Research": "0",
    "admit": "0.66"
  },
  {
    "sn": {"": "18"},
    "GRE": "319",
    "TOEFL": "106",
    "univRating": "3",
    "SOP": "4",
    "LOR": "3",
    "CGPA": "8",
    "Research": "1",
    "admit": "0.65"
  },
  {
    "sn": {"": "19"},
    "GRE": "318",
    "TOEFL": "110",
    "univRating": "3",
    "SOP": "4",
    "LOR": "3",
    "CGPA": "8.8",
    "Research": "0",
    "admit": "0.63"
  },
  {
    "sn": {"": "20"},
    "GRE": "303",
    "TOEFL": "102",
    "univRating": "3",
    "SOP": "3.5",
    "LOR": "3",
    "CGPA": "8.5",
    "Research": "0",
    "admit": "0.62"
  },
  {
    "sn": {"": "21"},
    "GRE": "312",
    "TOEFL": "107",
    "univRating": "3",
    "SOP": "3",
    "LOR": "2",
    "CGPA": "7.9",
    "Research": "1",
    "admit": "0.64"
  },
  {
    "sn": {"": "22"},
    "GRE": "325",
    "TOEFL": "114",
    "univRating": "4",
    "SOP": "3",
    "LOR": "2",
    "CGPA": "8.4",
    "Research": "0",
    "admit": "0.7"
  },
  {
    "sn": {"": "23"},
    "GRE": "328",
    "TOEFL": "116",
    "univRating": "5",
    "SOP": "5",
    "LOR": "5",
    "CGPA": "9.5",
    "Research": "1",
    "admit": "0.94"
  },
  {
    "sn": {"": "24"},
    "GRE": "334",
    "TOEFL": "119",
    "univRating": "5",
    "SOP": "5",
    "LOR": "4.5",
    "CGPA": "9.7",
    "Research": "1",
    "admit": "0.95"
  },
  {
    "sn": {"": "25"},
    "GRE": "336",
    "TOEFL": "119",
    "univRating": "5",
    "SOP": "4",
    "LOR": "3.5",
    "CGPA": "9.8",
    "Research": "1",
    "admit": "0.97"
  },
  {
    "sn": {"": "26"},
    "GRE": "340",
    "TOEFL": "120",
    "univRating": "5",
    "SOP": "4.5",
    "LOR": "4.5",
    "CGPA": "9.6",
    "Research": "1",
    "admit": "0.94"
  },
  {
    "sn": {"": "27"},
    "GRE": "322",
    "TOEFL": "109",
    "univRating": "5",
    "SOP": "4.5",
    "LOR": "3.5",
    "CGPA": "8.8",
    "Research": "0",
    "admit": "0.76"
  },
  {
    "sn": {"": "28"},
    "GRE": "298",
    "TOEFL": "98",
    "univRating": "2",
    "SOP": "1.5",
    "LOR": "2.5",
    "CGPA": "7.5",
    "Research": "1",
    "admit": "0.44"
  },
  {
    "sn": {"": "29"},
    "GRE": "295",
    "TOEFL": "93",
    "univRating": "1",
    "SOP": "2",
    "LOR": "2",
    "CGPA": "7.2",
    "Research": "0",
    "admit": "0.46"
  },
  {
    "sn": {"": "30"},
    "GRE": "310",
    "TOEFL": "99",
    "univRating": "2",
    "SOP": "1.5",
    "LOR": "2",
    "CGPA": "7.3",
    "Research": "0",
    "admit": "0.54"
  },
  {
    "sn": {"": "31"},
    "GRE": "300",
    "TOEFL": "97",
    "univRating": "2",
    "SOP": "3",
    "LOR": "3",
    "CGPA": "8.1",
    "Research": "1",
    "admit": "0.65"
  },
  {
    "sn": {"": "32"},
    "GRE": "327",
    "TOEFL": "103",
    "univRating": "3",
    "SOP": "4",
    "LOR": "4",
    "CGPA": "8.3",
    "Research": "1",
    "admit": "0.74"
  },
  {
    "sn": {"": "33"},
    "GRE": "338",
    "TOEFL": "118",
    "univRating": "4",
    "SOP": "3",
    "LOR": "4.5",
    "CGPA": "9.4",
    "Research": "1",
    "admit": "0.91"
  },
  {
    "sn": {"": "34"},
    "GRE": "340",
    "TOEFL": "114",
    "univRating": "5",
    "SOP": "4",
    "LOR": "4",
    "CGPA": "9.6",
    "Research": "1",
    "admit": "0.9"
  },
  {
    "sn": {"": "35"},
    "GRE": "331",
    "TOEFL": "112",
    "univRating": "5",
    "SOP": "4",
    "LOR": "5",
    "CGPA": "9.8",
    "Research": "1",
    "admit": "0.94"
  },
  {
    "sn": {"": "36"},
    "GRE": "320",
    "TOEFL": "110",
    "univRating": "5",
    "SOP": "5",
    "LOR": "5",
    "CGPA": "9.2",
    "Research": "1",
    "admit": "0.88"
  },
  {
    "sn": {"": "37"},
    "GRE": "299",
    "TOEFL": "106",
    "univRating": "2",
    "SOP": "4",
    "LOR": "4",
    "CGPA": "8.4",
    "Research": "0",
    "admit": "0.64"
  },
  {
    "sn": {"": "38"},
    "GRE": "300",
    "TOEFL": "105",
    "univRating": "1",
    "SOP": "1",
    "LOR": "2",
    "CGPA": "7.8",
    "Research": "0",
    "admit": "0.58"
  },
  {
    "sn": {"": "39"},
    "GRE": "304",
    "TOEFL": "105",
    "univRating": "1",
    "SOP": "3",
    "LOR": "1.5",
    "CGPA": "7.5",
    "Research": "0",
    "admit": "0.52"
  },
  {
    "sn": {"": "40"},
    "GRE": "307",
    "TOEFL": "108",
    "univRating": "2",
    "SOP": "4",
    "LOR": "3.5",
    "CGPA": "7.7",
    "Research": "0",
    "admit": "0.48"
  },
  {
    "sn": {"": "41"},
    "GRE": "308",
    "TOEFL": "110",
    "univRating": "3",
    "SOP": "3.5",
    "LOR": "3",
    "CGPA": "8",
    "Research": "1",
    "admit": "0.46"
  },
  {
    "sn": {"": "42"},
    "GRE": "316",
    "TOEFL": "105",
    "univRating": "2",
    "SOP": "2.5",
    "LOR": "2.5",
    "CGPA": "8.2",
    "Research": "1",
    "admit": "0.49"
  },
  {
    "sn": {"": "43"},
    "GRE": "313",
    "TOEFL": "107",
    "univRating": "2",
    "SOP": "2.5",
    "LOR": "2",
    "CGPA": "8.5",
    "Research": "1",
    "admit": "0.53"
  },
  {
    "sn": {"": "44"},
    "GRE": "332",
    "TOEFL": "117",
    "univRating": "4",
    "SOP": "4.5",
    "LOR": "4",
    "CGPA": "9.1",
    "Research": "0",
    "admit": "0.87"
  },
  {
    "sn": {"": "45"},
    "GRE": "326",
    "TOEFL": "113",
    "univRating": "5",
    "SOP": "4.5",
    "LOR": "4",
    "CGPA": "9.4",
    "Research": "1",
    "admit": "0.91"
  },
  {
    "sn": {"": "46"},
    "GRE": "322",
    "TOEFL": "110",
    "univRating": "5",
    "SOP": "5",
    "LOR": "4",
    "CGPA": "9.1",
    "Research": "1",
    "admit": "0.88"
  },
  {
    "sn": {"": "47"},
    "GRE": "329",
    "TOEFL": "114",
    "univRating": "5",
    "SOP": "4",
    "LOR": "5",
    "CGPA": "9.3",
    "Research": "1",
    "admit": "0.86"
  },
  {
    "sn": {"": "48"},
    "GRE": "339",
    "TOEFL": "119",
    "univRating": "5",
    "SOP": "4.5",
    "LOR": "4",
    "CGPA": "9.7",
    "Research": "0",
    "admit": "0.89"
  },
  {
    "sn": {"": "49"},
    "GRE": "321",
    "TOEFL": "110",
    "univRating": "3",
    "SOP": "3.5",
    "LOR": "5",
    "CGPA": "8.85",
    "Research": "1",
    "admit": "0.82"
  },
  {
    "sn": {"": "50"},
    "GRE": "327",
    "TOEFL": "111",
    "univRating": "4",
    "SOP": "3",
    "LOR": "4",
    "CGPA": "8.4",
    "Research": "1",
    "admit": "0.78"
  },
  {
    "sn": {"": "51"},
    "GRE": "313",
    "TOEFL": "98",
    "univRating": "3",
    "SOP": "2.5",
    "LOR": "4.5",
    "CGPA": "8.3",
    "Research": "1",
    "admit": "0.76"
  },
  {
    "sn": {"": "52"},
    "GRE": "312",
    "TOEFL": "100",
    "univRating": "2",
    "SOP": "1.5",
    "LOR": "3.5",
    "CGPA": "7.9",
    "Research": "1",
    "admit": "0.56"
  },
  {
    "sn": {"": "53"},
    "GRE": "334",
    "TOEFL": "116",
    "univRating": "4",
    "SOP": "4",
    "LOR": "3",
    "CGPA": "8",
    "Research": "1",
    "admit": "0.78"
  },
  {
    "sn": {"": "54"},
    "GRE": "324",
    "TOEFL": "112",
    "univRating": "4",
    "SOP": "4",
    "LOR": "2.5",
    "CGPA": "8.1",
    "Research": "1",
    "admit": "0.72"
  },
  {
    "sn": {"": "55"},
    "GRE": "322",
    "TOEFL": "110",
    "univRating": "3",
    "SOP": "3",
    "LOR": "3.5",
    "CGPA": "8",
    "Research": "0",
    "admit": "0.7"
  },
  {
    "sn": {"": "56"},
    "GRE": "320",
    "TOEFL": "103",
    "univRating": "3",
    "SOP": "3",
    "LOR": "3",
    "CGPA": "7.7",
    "Research": "0",
    "admit": "0.64"
  },
  {
    "sn": {"": "57"},
    "GRE": "316",
    "TOEFL": "102",
    "univRating": "3",
    "SOP": "2",
    "LOR": "3",
    "CGPA": "7.4",
    "Research": "0",
    "admit": "0.64"
  },
  {
    "sn": {"": "58"},
    "GRE": "298",
    "TOEFL": "99",
    "univRating": "2",
    "SOP": "4",
    "LOR": "2",
    "CGPA": "7.6",
    "Research": "0",
    "admit": "0.46"
  },
  {
    "sn": {"": "59"},
    "GRE": "300",
    "TOEFL": "99",
    "univRating": "1",
    "SOP": "3",
    "LOR": "2",
    "CGPA": "6.8",
    "Research": "1",
    "admit": "0.36"
  },
  {
    "sn": {"": "60"},
    "GRE": "311",
    "TOEFL": "104",
    "univRating": "2",
    "SOP": "2",
    "LOR": "2",
    "CGPA": "8.3",
    "Research": "0",
    "admit": "0.42"
  },
  {
    "sn": {"": "61"},
    "GRE": "309",
    "TOEFL": "100",
    "univRating": "2",
    "SOP": "3",
    "LOR": "3",
    "CGPA": "8.1",
    "Research": "0",
    "admit": "0.48"
  },
  {
    "sn": {"": "62"},
    "GRE": "307",
    "TOEFL": "101",
    "univRating": "3",
    "SOP": "4",
    "LOR": "3",
    "CGPA": "8.2",
    "Research": "0",
    "admit": "0.47"
  },
  {
    "sn": {"": "63"},
    "GRE": "304",
    "TOEFL": "105",
    "univRating": "2",
    "SOP": "3",
    "LOR": "3",
    "CGPA": "8.2",
    "Research": "1",
    "admit": "0.54"
  },
  {
    "sn": {"": "64"},
    "GRE": "315",
    "TOEFL": "107",
    "univRating": "2",
    "SOP": "4",
    "LOR": "3",
    "CGPA": "8.5",
    "Research": "1",
    "admit": "0.56"
  },
  {
    "sn": {"": "65"},
    "GRE": "325",
    "TOEFL": "111",
    "univRating": "3",
    "SOP": "3",
    "LOR": "3.5",
    "CGPA": "8.7",
    "Research": "0",
    "admit": "0.52"
  },
  {
    "sn": {"": "66"},
    "GRE": "325",
    "TOEFL": "112",
    "univRating": "4",
    "SOP": "3.5",
    "LOR": "3.5",
    "CGPA": "8.92",
    "Research": "0",
    "admit": "0.55"
  },
  {
    "sn": {"": "67"},
    "GRE": "327",
    "TOEFL": "114",
    "univRating": "3",
    "SOP": "3",
    "LOR": "3",
    "CGPA": "9.02",
    "Research": "0",
    "admit": "0.61"
  },
  {
    "sn": {"": "68"},
    "GRE": "316",
    "TOEFL": "107",
    "univRating": "2",
    "SOP": "3.5",
    "LOR": "3.5",
    "CGPA": "8.64",
    "Research": "1",
    "admit": "0.57"
  },
  {
    "sn": {"": "69"},
    "GRE": "318",
    "TOEFL": "109",
    "univRating": "3",
    "SOP": "3.5",
    "LOR": "4",
    "CGPA": "9.22",
    "Research": "1",
    "admit": "0.68"
  },
  {
    "sn": {"": "70"},
    "GRE": "328",
    "TOEFL": "115",
    "univRating": "4",
    "SOP": "4.5",
    "LOR": "4",
    "CGPA": "9.16",
    "Research": "1",
    "admit": "0.78"
  },
  {
    "sn": {"": "71"},
    "GRE": "332",
    "TOEFL": "118",
    "univRating": "5",
    "SOP": "5",
    "LOR": "5",
    "CGPA": "9.64",
    "Research": "1",
    "admit": "0.94"
  },
  {
    "sn": {"": "72"},
    "GRE": "336",
    "TOEFL": "112",
    "univRating": "5",
    "SOP": "5",
    "LOR": "5",
    "CGPA": "9.76",
    "Research": "1",
    "admit": "0.96"
  },
  {
    "sn": {"": "73"},
    "GRE": "321",
    "TOEFL": "111",
    "univRating": "5",
    "SOP": "5",
    "LOR": "5",
    "CGPA": "9.45",
    "Research": "1",
    "admit": "0.93"
  },
  {
    "sn": {"": "74"},
    "GRE": "314",
    "TOEFL": "108",
    "univRating": "4",
    "SOP": "4.5",
    "LOR": "4",
    "CGPA": "9.04",
    "Research": "1",
    "admit": "0.84"
  },
  {
    "sn": {"": "75"},
    "GRE": "314",
    "TOEFL": "106",
    "univRating": "3",
    "SOP": "3",
    "LOR": "5",
    "CGPA": "8.9",
    "Research": "0",
    "admit": "0.74"
  },
  {
    "sn": {"": "76"},
    "GRE": "329",
    "TOEFL": "114",
    "univRating": "2",
    "SOP": "2",
    "LOR": "4",
    "CGPA": "8.56",
    "Research": "1",
    "admit": "0.72"
  },
  {
    "sn": {"": "77"},
    "GRE": "327",
    "TOEFL": "112",
    "univRating": "3",
    "SOP": "3",
    "LOR": "3",
    "CGPA": "8.72",
    "Research": "1",
    "admit": "0.74"
  },
  {
    "sn": {"": "78"},
    "GRE": "301",
    "TOEFL": "99",
    "univRating": "2",
    "SOP": "3",
    "LOR": "2",
    "CGPA": "8.22",
    "Research": "0",
    "admit": "0.64"
  },
  {
    "sn": {"": "79"},
    "GRE": "296",
    "TOEFL": "95",
    "univRating": "2",
    "SOP": "3",
    "LOR": "2",
    "CGPA": "7.54",
    "Research": "1",
    "admit": "0.44"
  },
  {
    "sn": {"": "80"},
    "GRE": "294",
    "TOEFL": "93",
    "univRating": "1",
    "SOP": "1.5",
    "LOR": "2",
    "CGPA": "7.36",
    "Research": "0",
    "admit": "0.46"
  },
  {
    "sn": {"": "81"},
    "GRE": "312",
    "TOEFL": "105",
    "univRating": "3",
    "SOP": "2",
    "LOR": "3",
    "CGPA": "8.02",
    "Research": "1",
    "admit": "0.5"
  },
  {
    "sn": {"": "82"},
    "GRE": "340",
    "TOEFL": "120",
    "univRating": "4",
    "SOP": "5",
    "LOR": "5",
    "CGPA": "9.5",
    "Research": "1",
    "admit": "0.96"
  },
  {
    "sn": {"": "83"},
    "GRE": "320",
    "TOEFL": "110",
    "univRating": "5",
    "SOP": "5",
    "LOR": "4.5",
    "CGPA": "9.22",
    "Research": "1",
    "admit": "0.92"
  },
  {
    "sn": {"": "84"},
    "GRE": "322",
    "TOEFL": "115",
    "univRating": "5",
    "SOP": "4",
    "LOR": "4.5",
    "CGPA": "9.36",
    "Research": "1",
    "admit": "0.92"
  },
  {
    "sn": {"": "85"},
    "GRE": "340",
    "TOEFL": "115",
    "univRating": "5",
    "SOP": "4.5",
    "LOR": "4.5",
    "CGPA": "9.45",
    "Research": "1",
    "admit": "0.94"
  },
  {
    "sn": {"": "86"},
    "GRE": "319",
    "TOEFL": "103",
    "univRating": "4",
    "SOP": "4.5",
    "LOR": "3.5",
    "CGPA": "8.66",
    "Research": "0",
    "admit": "0.76"
  },
  {
    "sn": {"": "87"},
    "GRE": "315",
    "TOEFL": "106",
    "univRating": "3",
    "SOP": "4.5",
    "LOR": "3.5",
    "CGPA": "8.42",
    "Research": "0",
    "admit": "0.72"
  },
  {
    "sn": {"": "88"},
    "GRE": "317",
    "TOEFL": "107",
    "univRating": "2",
    "SOP": "3.5",
    "LOR": "3",
    "CGPA": "8.28",
    "Research": "0",
    "admit": "0.66"
  },
  {
    "sn": {"": "89"},
    "GRE": "314",
    "TOEFL": "108",
    "univRating": "3",
    "SOP": "4.5",
    "LOR": "3.5",
    "CGPA": "8.14",
    "Research": "0",
    "admit": "0.64"
  },
  {
    "sn": {"": "90"},
    "GRE": "316",
    "TOEFL": "109",
    "univRating": "4",
    "SOP": "4.5",
    "LOR": "3.5",
    "CGPA": "8.76",
    "Research": "1",
    "admit": "0.74"
  },
  {
    "sn": {"": "91"},
    "GRE": "318",
    "TOEFL": "106",
    "univRating": "2",
    "SOP": "4",
    "LOR": "4",
    "CGPA": "7.92",
    "Research": "1",
    "admit": "0.64"
  },
  {
    "sn": {"": "92"},
    "GRE": "299",
    "TOEFL": "97",
    "univRating": "3",
    "SOP": "5",
    "LOR": "3.5",
    "CGPA": "7.66",
    "Research": "0",
    "admit": "0.38"
  },
  {
    "sn": {"": "93"},
    "GRE": "298",
    "TOEFL": "98",
    "univRating": "2",
    "SOP": "4",
    "LOR": "3",
    "CGPA": "8.03",
    "Research": "0",
    "admit": "0.34"
  },
  {
    "sn": {"": "94"},
    "GRE": "301",
    "TOEFL": "97",
    "univRating": "2",
    "SOP": "3",
    "LOR": "3",
    "CGPA": "7.88",
    "Research": "1",
    "admit": "0.44"
  },
  {
    "sn": {"": "95"},
    "GRE": "303",
    "TOEFL": "99",
    "univRating": "3",
    "SOP": "2",
    "LOR": "2.5",
    "CGPA": "7.66",
    "Research": "0",
    "admit": "0.36"
  },
  {
    "sn": {"": "96"},
    "GRE": "304",
    "TOEFL": "100",
    "univRating": "4",
    "SOP": "1.5",
    "LOR": "2.5",
    "CGPA": "7.84",
    "Research": "0",
    "admit": "0.42"
  },
  {
    "sn": {"": "97"},
    "GRE": "306",
    "TOEFL": "100",
    "univRating": "2",
    "SOP": "3",
    "LOR": "3",
    "CGPA": "8",
    "Research": "0",
    "admit": "0.48"
  },
  {
    "sn": {"": "98"},
    "GRE": "331",
    "TOEFL": "120",
    "univRating": "3",
    "SOP": "4",
    "LOR": "4",
    "CGPA": "8.96",
    "Research": "1",
    "admit": "0.86"
  },
  {
    "sn": {"": "99"},
    "GRE": "332",
    "TOEFL": "119",
    "univRating": "4",
    "SOP": "5",
    "LOR": "4.5",
    "CGPA": "9.24",
    "Research": "1",
    "admit": "0.9"
  },
  {
    "sn": {"": "100"},
    "GRE": "323",
    "TOEFL": "113",
    "univRating": "3",
    "SOP": "4",
    "LOR": "4",
    "CGPA": "8.88",
    "Research": "1",
    "admit": "0.79"
  },
  {
    "sn": {"": "101"},
    "GRE": "322",
    "TOEFL": "107",
    "univRating": "3",
    "SOP": "3.5",
    "LOR": "3.5",
    "CGPA": "8.46",
    "Research": "1",
    "admit": "0.71"
  },
  {
    "sn": {"": "102"},
    "GRE": "312",
    "TOEFL": "105",
    "univRating": "2",
    "SOP": "2.5",
    "LOR": "3",
    "CGPA": "8.12",
    "Research": "0",
    "admit": "0.64"
  },
  {
    "sn": {"": "103"},
    "GRE": "314",
    "TOEFL": "106",
    "univRating": "2",
    "SOP": "4",
    "LOR": "3.5",
    "CGPA": "8.25",
    "Research": "0",
    "admit": "0.62"
  },
  {
    "sn": {"": "104"},
    "GRE": "317",
    "TOEFL": "104",
    "univRating": "2",
    "SOP": "4.5",
    "LOR": "4",
    "CGPA": "8.47",
    "Research": "0",
    "admit": "0.57"
  },
  {
    "sn": {"": "105"},
    "GRE": "326",
    "TOEFL": "112",
    "univRating": "3",
    "SOP": "3.5",
    "LOR": "3",
    "CGPA": "9.05",
    "Research": "1",
    "admit": "0.74"
  },
  {
    "sn": {"": "106"},
    "GRE": "316",
    "TOEFL": "110",
    "univRating": "3",
    "SOP": "4",
    "LOR": "4.5",
    "CGPA": "8.78",
    "Research": "1",
    "admit": "0.69"
  },
  {
    "sn": {"": "107"},
    "GRE": "329",
    "TOEFL": "111",
    "univRating": "4",
    "SOP": "4.5",
    "LOR": "4.5",
    "CGPA": "9.18",
    "Research": "1",
    "admit": "0.87"
  },
  {
    "sn": {"": "108"},
    "GRE": "338",
    "TOEFL": "117",
    "univRating": "4",
    "SOP": "3.5",
    "LOR": "4.5",
    "CGPA": "9.46",
    "Research": "1",
    "admit": "0.91"
  },
  {
    "sn": {"": "109"},
    "GRE": "331",
    "TOEFL": "116",
    "univRating": "5",
    "SOP": "5",
    "LOR": "5",
    "CGPA": "9.38",
    "Research": "1",
    "admit": "0.93"
  },
  {
    "sn": {"": "110"},
    "GRE": "304",
    "TOEFL": "103",
    "univRating": "5",
    "SOP": "5",
    "LOR": "4",
    "CGPA": "8.64",
    "Research": "0",
    "admit": "0.68"
  },
  {
    "sn": {"": "111"},
    "GRE": "305",
    "TOEFL": "108",
    "univRating": "5",
    "SOP": "3",
    "LOR": "3",
    "CGPA": "8.48",
    "Research": "0",
    "admit": "0.61"
  },
  {
    "sn": {"": "112"},
    "GRE": "321",
    "TOEFL": "109",
    "univRating": "4",
    "SOP": "4",
    "LOR": "4",
    "CGPA": "8.68",
    "Research": "1",
    "admit": "0.69"
  },
  {
    "sn": {"": "113"},
    "GRE": "301",
    "TOEFL": "107",
    "univRating": "3",
    "SOP": "3.5",
    "LOR": "3.5",
    "CGPA": "8.34",
    "Research": "1",
    "admit": "0.62"
  },
  {
    "sn": {"": "114"},
    "GRE": "320",
    "TOEFL": "110",
    "univRating": "2",
    "SOP": "4",
    "LOR": "3.5",
    "CGPA": "8.56",
    "Research": "0",
    "admit": "0.72"
  },
  {
    "sn": {"": "115"},
    "GRE": "311",
    "TOEFL": "105",
    "univRating": "3",
    "SOP": "3.5",
    "LOR": "3",
    "CGPA": "8.45",
    "Research": "1",
    "admit": "0.59"
  },
  {
    "sn": {"": "116"},
    "GRE": "310",
    "TOEFL": "106",
    "univRating": "4",
    "SOP": "4.5",
    "LOR": "4.5",
    "CGPA": "9.04",
    "Research": "1",
    "admit": "0.66"
  },
  {
    "sn": {"": "117"},
    "GRE": "299",
    "TOEFL": "102",
    "univRating": "3",
    "SOP": "4",
    "LOR": "3.5",
    "CGPA": "8.62",
    "Research": "0",
    "admit": "0.56"
  },
  {
    "sn": {"": "118"},
    "GRE": "290",
    "TOEFL": "104",
    "univRating": "4",
    "SOP": "2",
    "LOR": "2.5",
    "CGPA": "7.46",
    "Research": "0",
    "admit": "0.45"
  },
  {
    "sn": {"": "119"},
    "GRE": "296",
    "TOEFL": "99",
    "univRating": "2",
    "SOP": "3",
    "LOR": "3.5",
    "CGPA": "7.28",
    "Research": "0",
    "admit": "0.47"
  },
  {
    "sn": {"": "120"},
    "GRE": "327",
    "TOEFL": "104",
    "univRating": "5",
    "SOP": "3",
    "LOR": "3.5",
    "CGPA": "8.84",
    "Research": "1",
    "admit": "0.71"
  },
  {
    "sn": {"": "121"},
    "GRE": "335",
    "TOEFL": "117",
    "univRating": "5",
    "SOP": "5",
    "LOR": "5",
    "CGPA": "9.56",
    "Research": "1",
    "admit": "0.94"
  },
  {
    "sn": {"": "122"},
    "GRE": "334",
    "TOEFL": "119",
    "univRating": "5",
    "SOP": "4.5",
    "LOR": "4.5",
    "CGPA": "9.48",
    "Research": "1",
    "admit": "0.94"
  },
  {
    "sn": {"": "123"},
    "GRE": "310",
    "TOEFL": "106",
    "univRating": "4",
    "SOP": "1.5",
    "LOR": "2.5",
    "CGPA": "8.36",
    "Research": "0",
    "admit": "0.57"
  },
  {
    "sn": {"": "124"},
    "GRE": "308",
    "TOEFL": "108",
    "univRating": "3",
    "SOP": "3.5",
    "LOR": "3.5",
    "CGPA": "8.22",
    "Research": "0",
    "admit": "0.61"
  },
  {
    "sn": {"": "125"},
    "GRE": "301",
    "TOEFL": "106",
    "univRating": "4",
    "SOP": "2.5",
    "LOR": "3",
    "CGPA": "8.47",
    "Research": "0",
    "admit": "0.57"
  },
  {
    "sn": {"": "126"},
    "GRE": "300",
    "TOEFL": "100",
    "univRating": "3",
    "SOP": "2",
    "LOR": "3",
    "CGPA": "8.66",
    "Research": "1",
    "admit": "0.64"
  },
  {
    "sn": {"": "127"},
    "GRE": "323",
    "TOEFL": "113",
    "univRating": "3",
    "SOP": "4",
    "LOR": "3",
    "CGPA": "9.32",
    "Research": "1",
    "admit": "0.85"
  },
  {
    "sn": {"": "128"},
    "GRE": "319",
    "TOEFL": "112",
    "univRating": "3",
    "SOP": "2.5",
    "LOR": "2",
    "CGPA": "8.71",
    "Research": "1",
    "admit": "0.78"
  },
  {
    "sn": {"": "129"},
    "GRE": "326",
    "TOEFL": "112",
    "univRating": "3",
    "SOP": "3.5",
    "LOR": "3",
    "CGPA": "9.1",
    "Research": "1",
    "admit": "0.84"
  },
  {
    "sn": {"": "130"},
    "GRE": "333",
    "TOEFL": "118",
    "univRating": "5",
    "SOP": "5",
    "LOR": "5",
    "CGPA": "9.35",
    "Research": "1",
    "admit": "0.92"
  },
  {
    "sn": {"": "131"},
    "GRE": "339",
    "TOEFL": "114",
    "univRating": "5",
    "SOP": "4",
    "LOR": "4.5",
    "CGPA": "9.76",
    "Research": "1",
    "admit": "0.96"
  },
  {
    "sn": {"": "132"},
    "GRE": "303",
    "TOEFL": "105",
    "univRating": "5",
    "SOP": "5",
    "LOR": "4.5",
    "CGPA": "8.65",
    "Research": "0",
    "admit": "0.77"
  },
  {
    "sn": {"": "133"},
    "GRE": "309",
    "TOEFL": "105",
    "univRating": "5",
    "SOP": "3.5",
    "LOR": "3.5",
    "CGPA": "8.56",
    "Research": "0",
    "admit": "0.71"
  },
  {
    "sn": {"": "134"},
    "GRE": "323",
    "TOEFL": "112",
    "univRating": "5",
    "SOP": "4",
    "LOR": "4.5",
    "CGPA": "8.78",
    "Research": "0",
    "admit": "0.79"
  },
  {
    "sn": {"": "135"},
    "GRE": "333",
    "TOEFL": "113",
    "univRating": "5",
    "SOP": "4",
    "LOR": "4",
    "CGPA": "9.28",
    "Research": "1",
    "admit": "0.89"
  },
  {
    "sn": {"": "136"},
    "GRE": "314",
    "TOEFL": "109",
    "univRating": "4",
    "SOP": "3.5",
    "LOR": "4",
    "CGPA": "8.77",
    "Research": "1",
    "admit": "0.82"
  },
  {
    "sn": {"": "137"},
    "GRE": "312",
    "TOEFL": "103",
    "univRating": "3",
    "SOP": "5",
    "LOR": "4",
    "CGPA": "8.45",
    "Research": "0",
    "admit": "0.76"
  },
  {
    "sn": {"": "138"},
    "GRE": "316",
    "TOEFL": "100",
    "univRating": "2",
    "SOP": "1.5",
    "LOR": "3",
    "CGPA": "8.16",
    "Research": "1",
    "admit": "0.71"
  },
  {
    "sn": {"": "139"},
    "GRE": "326",
    "TOEFL": "116",
    "univRating": "2",
    "SOP": "4.5",
    "LOR": "3",
    "CGPA": "9.08",
    "Research": "1",
    "admit": "0.8"
  },
  {
    "sn": {"": "140"},
    "GRE": "318",
    "TOEFL": "109",
    "univRating": "1",
    "SOP": "3.5",
    "LOR": "3.5",
    "CGPA": "9.12",
    "Research": "0",
    "admit": "0.78"
  },
  {
    "sn": {"": "141"},
    "GRE": "329",
    "TOEFL": "110",
    "univRating": "2",
    "SOP": "4",
    "LOR": "3",
    "CGPA": "9.15",
    "Research": "1",
    "admit": "0.84"
  },
  {
    "sn": {"": "142"},
    "GRE": "332",
    "TOEFL": "118",
    "univRating": "2",
    "SOP": "4.5",
    "LOR": "3.5",
    "CGPA": "9.36",
    "Research": "1",
    "admit": "0.9"
  },
  {
    "sn": {"": "143"},
    "GRE": "331",
    "TOEFL": "115",
    "univRating": "5",
    "SOP": "4",
    "LOR": "3.5",
    "CGPA": "9.44",
    "Research": "1",
    "admit": "0.92"
  },
  {
    "sn": {"": "144"},
    "GRE": "340",
    "TOEFL": "120",
    "univRating": "4",
    "SOP": "4.5",
    "LOR": "4",
    "CGPA": "9.92",
    "Research": "1",
    "admit": "0.97"
  },
  {
    "sn": {"": "145"},
    "GRE": "325",
    "TOEFL": "112",
    "univRating": "2",
    "SOP": "3",
    "LOR": "3.5",
    "CGPA": "8.96",
    "Research": "1",
    "admit": "0.8"
  },
  {
    "sn": {"": "146"},
    "GRE": "320",
    "TOEFL": "113",
    "univRating": "2",
    "SOP": "2",
    "LOR": "2.5",
    "CGPA": "8.64",
    "Research": "1",
    "admit": "0.81"
  },
  {
    "sn": {"": "147"},
    "GRE": "315",
    "TOEFL": "105",
    "univRating": "3",
    "SOP": "2",
    "LOR": "2.5",
    "CGPA": "8.48",
    "Research": "0",
    "admit": "0.75"
  },
  {
    "sn": {"": "148"},
    "GRE": "326",
    "TOEFL": "114",
    "univRating": "3",
    "SOP": "3",
    "LOR": "3",
    "CGPA": "9.11",
    "Research": "1",
    "admit": "0.83"
  },
  {
    "sn": {"": "149"},
    "GRE": "339",
    "TOEFL": "116",
    "univRating": "4",
    "SOP": "4",
    "LOR": "3.5",
    "CGPA": "9.8",
    "Research": "1",
    "admit": "0.96"
  },
  {
    "sn": {"": "150"},
    "GRE": "311",
    "TOEFL": "106",
    "univRating": "2",
    "SOP": "3.5",
    "LOR": "3",
    "CGPA": "8.26",
    "Research": "1",
    "admit": "0.79"
  },
  {
    "sn": {"": "151"},
    "GRE": "334",
    "TOEFL": "114",
    "univRating": "4",
    "SOP": "4",
    "LOR": "4",
    "CGPA": "9.43",
    "Research": "1",
    "admit": "0.93"
  },
  {
    "sn": {"": "152"},
    "GRE": "332",
    "TOEFL": "116",
    "univRating": "5",
    "SOP": "5",
    "LOR": "5",
    "CGPA": "9.28",
    "Research": "1",
    "admit": "0.94"
  },
  {
    "sn": {"": "153"},
    "GRE": "321",
    "TOEFL": "112",
    "univRating": "5",
    "SOP": "5",
    "LOR": "5",
    "CGPA": "9.06",
    "Research": "1",
    "admit": "0.86"
  },
  {
    "sn": {"": "154"},
    "GRE": "324",
    "TOEFL": "105",
    "univRating": "3",
    "SOP": "3",
    "LOR": "4",
    "CGPA": "8.75",
    "Research": "0",
    "admit": "0.79"
  },
  {
    "sn": {"": "155"},
    "GRE": "326",
    "TOEFL": "108",
    "univRating": "3",
    "SOP": "3",
    "LOR": "3.5",
    "CGPA": "8.89",
    "Research": "0",
    "admit": "0.8"
  },
  {
    "sn": {"": "156"},
    "GRE": "312",
    "TOEFL": "109",
    "univRating": "3",
    "SOP": "3",
    "LOR": "3",
    "CGPA": "8.69",
    "Research": "0",
    "admit": "0.77"
  },
  {
    "sn": {"": "157"},
    "GRE": "315",
    "TOEFL": "105",
    "univRating": "3",
    "SOP": "2",
    "LOR": "2.5",
    "CGPA": "8.34",
    "Research": "0",
    "admit": "0.7"
  },
  {
    "sn": {"": "158"},
    "GRE": "309",
    "TOEFL": "104",
    "univRating": "2",
    "SOP": "2",
    "LOR": "2.5",
    "CGPA": "8.26",
    "Research": "0",
    "admit": "0.65"
  },
  {
    "sn": {"": "159"},
    "GRE": "306",
    "TOEFL": "106",
    "univRating": "2",
    "SOP": "2",
    "LOR": "2.5",
    "CGPA": "8.14",
    "Research": "0",
    "admit": "0.61"
  },
  {
    "sn": {"": "160"},
    "GRE": "297",
    "TOEFL": "100",
    "univRating": "1",
    "SOP": "1.5",
    "LOR": "2",
    "CGPA": "7.9",
    "Research": "0",
    "admit": "0.52"
  },
  {
    "sn": {"": "161"},
    "GRE": "315",
    "TOEFL": "103",
    "univRating": "1",
    "SOP": "1.5",
    "LOR": "2",
    "CGPA": "7.86",
    "Research": "0",
    "admit": "0.57"
  },
  {
    "sn": {"": "162"},
    "GRE": "298",
    "TOEFL": "99",
    "univRating": "1",
    "SOP": "1.5",
    "LOR": "3",
    "CGPA": "7.46",
    "Research": "0",
    "admit": "0.53"
  },
  {
    "sn": {"": "163"},
    "GRE": "318",
    "TOEFL": "109",
    "univRating": "3",
    "SOP": "3",
    "LOR": "3",
    "CGPA": "8.5",
    "Research": "0",
    "admit": "0.67"
  },
  {
    "sn": {"": "164"},
    "GRE": "317",
    "TOEFL": "105",
    "univRating": "3",
    "SOP": "3.5",
    "LOR": "3",
    "CGPA": "8.56",
    "Research": "0",
    "admit": "0.68"
  },
  {
    "sn": {"": "165"},
    "GRE": "329",
    "TOEFL": "111",
    "univRating": "4",
    "SOP": "4.5",
    "LOR": "4",
    "CGPA": "9.01",
    "Research": "1",
    "admit": "0.81"
  },
  {
    "sn": {"": "166"},
    "GRE": "322",
    "TOEFL": "110",
    "univRating": "5",
    "SOP": "4.5",
    "LOR": "4",
    "CGPA": "8.97",
    "Research": "0",
    "admit": "0.78"
  },
  {
    "sn": {"": "167"},
    "GRE": "302",
    "TOEFL": "102",
    "univRating": "3",
    "SOP": "3.5",
    "LOR": "5",
    "CGPA": "8.33",
    "Research": "0",
    "admit": "0.65"
  },
  {
    "sn": {"": "168"},
    "GRE": "313",
    "TOEFL": "102",
    "univRating": "3",
    "SOP": "2",
    "LOR": "3",
    "CGPA": "8.27",
    "Research": "0",
    "admit": "0.64"
  },
  {
    "sn": {"": "169"},
    "GRE": "293",
    "TOEFL": "97",
    "univRating": "2",
    "SOP": "2",
    "LOR": "4",
    "CGPA": "7.8",
    "Research": "1",
    "admit": "0.64"
  },
  {
    "sn": {"": "170"},
    "GRE": "311",
    "TOEFL": "99",
    "univRating": "2",
    "SOP": "2.5",
    "LOR": "3",
    "CGPA": "7.98",
    "Research": "0",
    "admit": "0.65"
  },
  {
    "sn": {"": "171"},
    "GRE": "312",
    "TOEFL": "101",
    "univRating": "2",
    "SOP": "2.5",
    "LOR": "3.5",
    "CGPA": "8.04",
    "Research": "1",
    "admit": "0.68"
  },
  {
    "sn": {"": "172"},
    "GRE": "334",
    "TOEFL": "117",
    "univRating": "5",
    "SOP": "4",
    "LOR": "4.5",
    "CGPA": "9.07",
    "Research": "1",
    "admit": "0.89"
  },
  {
    "sn": {"": "173"},
    "GRE": "322",
    "TOEFL": "110",
    "univRating": "4",
    "SOP": "4",
    "LOR": "5",
    "CGPA": "9.13",
    "Research": "1",
    "admit": "0.86"
  },
  {
    "sn": {"": "174"},
    "GRE": "323",
    "TOEFL": "113",
    "univRating": "4",
    "SOP": "4",
    "LOR": "4.5",
    "CGPA": "9.23",
    "Research": "1",
    "admit": "0.89"
  },
  {
    "sn": {"": "175"},
    "GRE": "321",
    "TOEFL": "111",
    "univRating": "4",
    "SOP": "4",
    "LOR": "4",
    "CGPA": "8.97",
    "Research": "1",
    "admit": "0.87"
  },
  {
    "sn": {"": "176"},
    "GRE": "320",
    "TOEFL": "111",
    "univRating": "4",
    "SOP": "4.5",
    "LOR": "3.5",
    "CGPA": "8.87",
    "Research": "1",
    "admit": "0.85"
  },
  {
    "sn": {"": "177"},
    "GRE": "329",
    "TOEFL": "119",
    "univRating": "4",
    "SOP": "4.5",
    "LOR": "4.5",
    "CGPA": "9.16",
    "Research": "1",
    "admit": "0.9"
  },
  {
    "sn": {"": "178"},
    "GRE": "319",
    "TOEFL": "110",
    "univRating": "3",
    "SOP": "3.5",
    "LOR": "3.5",
    "CGPA": "9.04",
    "Research": "0",
    "admit": "0.82"
  },
  {
    "sn": {"": "179"},
    "GRE": "309",
    "TOEFL": "108",
    "univRating": "3",
    "SOP": "2.5",
    "LOR": "3",
    "CGPA": "8.12",
    "Research": "0",
    "admit": "0.72"
  },
  {
    "sn": {"": "180"},
    "GRE": "307",
    "TOEFL": "102",
    "univRating": "3",
    "SOP": "3",
    "LOR": "3",
    "CGPA": "8.27",
    "Research": "0",
    "admit": "0.73"
  },
  {
    "sn": {"": "181"},
    "GRE": "300",
    "TOEFL": "104",
    "univRating": "3",
    "SOP": "3.5",
    "LOR": "3",
    "CGPA": "8.16",
    "Research": "0",
    "admit": "0.71"
  },
  {
    "sn": {"": "182"},
    "GRE": "305",
    "TOEFL": "107",
    "univRating": "2",
    "SOP": "2.5",
    "LOR": "2.5",
    "CGPA": "8.42",
    "Research": "0",
    "admit": "0.71"
  },
  {
    "sn": {"": "183"},
    "GRE": "299",
    "TOEFL": "100",
    "univRating": "2",
    "SOP": "3",
    "LOR": "3.5",
    "CGPA": "7.88",
    "Research": "0",
    "admit": "0.68"
  },
  {
    "sn": {"": "184"},
    "GRE": "314",
    "TOEFL": "110",
    "univRating": "3",
    "SOP": "4",
    "LOR": "4",
    "CGPA": "8.8",
    "Research": "0",
    "admit": "0.75"
  },
  {
    "sn": {"": "185"},
    "GRE": "316",
    "TOEFL": "106",
    "univRating": "2",
    "SOP": "2.5",
    "LOR": "4",
    "CGPA": "8.32",
    "Research": "0",
    "admit": "0.72"
  },
  {
    "sn": {"": "186"},
    "GRE": "327",
    "TOEFL": "113",
    "univRating": "4",
    "SOP": "4.5",
    "LOR": "4.5",
    "CGPA": "9.11",
    "Research": "1",
    "admit": "0.89"
  },
  {
    "sn": {"": "187"},
    "GRE": "317",
    "TOEFL": "107",
    "univRating": "3",
    "SOP": "3.5",
    "LOR": "3",
    "CGPA": "8.68",
    "Research": "1",
    "admit": "0.84"
  },
  {
    "sn": {"": "188"},
    "GRE": "335",
    "TOEFL": "118",
    "univRating": "5",
    "SOP": "4.5",
    "LOR": "3.5",
    "CGPA": "9.44",
    "Research": "1",
    "admit": "0.93"
  },
  {
    "sn": {"": "189"},
    "GRE": "331",
    "TOEFL": "115",
    "univRating": "5",
    "SOP": "4.5",
    "LOR": "3.5",
    "CGPA": "9.36",
    "Research": "1",
    "admit": "0.93"
  },
  {
    "sn": {"": "190"},
    "GRE": "324",
    "TOEFL": "112",
    "univRating": "5",
    "SOP": "5",
    "LOR": "5",
    "CGPA": "9.08",
    "Research": "1",
    "admit": "0.88"
  },
  {
    "sn": {"": "191"},
    "GRE": "324",
    "TOEFL": "111",
    "univRating": "5",
    "SOP": "4.5",
    "LOR": "4",
    "CGPA": "9.16",
    "Research": "1",
    "admit": "0.9"
  },
  {
    "sn": {"": "192"},
    "GRE": "323",
    "TOEFL": "110",
    "univRating": "5",
    "SOP": "4",
    "LOR": "5",
    "CGPA": "8.98",
    "Research": "1",
    "admit": "0.87"
  },
  {
    "sn": {"": "193"},
    "GRE": "322",
    "TOEFL": "114",
    "univRating": "5",
    "SOP": "4.5",
    "LOR": "4",
    "CGPA": "8.94",
    "Research": "1",
    "admit": "0.86"
  },
  {
    "sn": {"": "194"},
    "GRE": "336",
    "TOEFL": "118",
    "univRating": "5",
    "SOP": "4.5",
    "LOR": "5",
    "CGPA": "9.53",
    "Research": "1",
    "admit": "0.94"
  },
  {
    "sn": {"": "195"},
    "GRE": "316",
    "TOEFL": "109",
    "univRating": "3",
    "SOP": "3.5",
    "LOR": "3",
    "CGPA": "8.76",
    "Research": "0",
    "admit": "0.77"
  },
  {
    "sn": {"": "196"},
    "GRE": "307",
    "TOEFL": "107",
    "univRating": "2",
    "SOP": "3",
    "LOR": "3.5",
    "CGPA": "8.52",
    "Research": "1",
    "admit": "0.78"
  },
  {
    "sn": {"": "197"},
    "GRE": "306",
    "TOEFL": "105",
    "univRating": "2",
    "SOP": "3",
    "LOR": "2.5",
    "CGPA": "8.26",
    "Research": "0",
    "admit": "0.73"
  },
  {
    "sn": {"": "198"},
    "GRE": "310",
    "TOEFL": "106",
    "univRating": "2",
    "SOP": "3.5",
    "LOR": "2.5",
    "CGPA": "8.33",
    "Research": "0",
    "admit": "0.73"
  },
  {
    "sn": {"": "199"},
    "GRE": "311",
    "TOEFL": "104",
    "univRating": "3",
    "SOP": "4.5",
    "LOR": "4.5",
    "CGPA": "8.43",
    "Research": "0",
    "admit": "0.7"
  },
  {
    "sn": {"": "200"},
    "GRE": "313",
    "TOEFL": "107",
    "univRating": "3",
    "SOP": "4",
    "LOR": "4.5",
    "CGPA": "8.69",
    "Research": "0",
    "admit": "0.72"
  },
  {
    "sn": {"": "201"},
    "GRE": "317",
    "TOEFL": "103",
    "univRating": "3",
    "SOP": "2.5",
    "LOR": "3",
    "CGPA": "8.54",
    "Research": "1",
    "admit": "0.73"
  },
  {
    "sn": {"": "202"},
    "GRE": "315",
    "TOEFL": "110",
    "univRating": "2",
    "SOP": "3.5",
    "LOR": "3",
    "CGPA": "8.46",
    "Research": "1",
    "admit": "0.72"
  },
  {
    "sn": {"": "203"},
    "GRE": "340",
    "TOEFL": "120",
    "univRating": "5",
    "SOP": "4.5",
    "LOR": "4.5",
    "CGPA": "9.91",
    "Research": "1",
    "admit": "0.97"
  },
  {
    "sn": {"": "204"},
    "GRE": "334",
    "TOEFL": "120",
    "univRating": "5",
    "SOP": "4",
    "LOR": "5",
    "CGPA": "9.87",
    "Research": "1",
    "admit": "0.97"
  },
  {
    "sn": {"": "205"},
    "GRE": "298",
    "TOEFL": "105",
    "univRating": "3",
    "SOP": "3.5",
    "LOR": "4",
    "CGPA": "8.54",
    "Research": "0",
    "admit": "0.69"
  },
  {
    "sn": {"": "206"},
    "GRE": "295",
    "TOEFL": "99",
    "univRating": "2",
    "SOP": "2.5",
    "LOR": "3",
    "CGPA": "7.65",
    "Research": "0",
    "admit": "0.57"
  },
  {
    "sn": {"": "207"},
    "GRE": "315",
    "TOEFL": "99",
    "univRating": "2",
    "SOP": "3.5",
    "LOR": "3",
    "CGPA": "7.89",
    "Research": "0",
    "admit": "0.63"
  },
  {
    "sn": {"": "208"},
    "GRE": "310",
    "TOEFL": "102",
    "univRating": "3",
    "SOP": "3.5",
    "LOR": "4",
    "CGPA": "8.02",
    "Research": "1",
    "admit": "0.66"
  },
  {
    "sn": {"": "209"},
    "GRE": "305",
    "TOEFL": "106",
    "univRating": "2",
    "SOP": "3",
    "LOR": "3",
    "CGPA": "8.16",
    "Research": "0",
    "admit": "0.64"
  },
  {
    "sn": {"": "210"},
    "GRE": "301",
    "TOEFL": "104",
    "univRating": "3",
    "SOP": "3.5",
    "LOR": "4",
    "CGPA": "8.12",
    "Research": "1",
    "admit": "0.68"
  },
  {
    "sn": {"": "211"},
    "GRE": "325",
    "TOEFL": "108",
    "univRating": "4",
    "SOP": "4.5",
    "LOR": "4",
    "CGPA": "9.06",
    "Research": "1",
    "admit": "0.79"
  },
  {
    "sn": {"": "212"},
    "GRE": "328",
    "TOEFL": "110",
    "univRating": "4",
    "SOP": "5",
    "LOR": "4",
    "CGPA": "9.14",
    "Research": "1",
    "admit": "0.82"
  },
  {
    "sn": {"": "213"},
    "GRE": "338",
    "TOEFL": "120",
    "univRating": "4",
    "SOP": "5",
    "LOR": "5",
    "CGPA": "9.66",
    "Research": "1",
    "admit": "0.95"
  },
  {
    "sn": {"": "214"},
    "GRE": "333",
    "TOEFL": "119",
    "univRating": "5",
    "SOP": "5",
    "LOR": "4.5",
    "CGPA": "9.78",
    "Research": "1",
    "admit": "0.96"
  },
  {
    "sn": {"": "215"},
    "GRE": "331",
    "TOEFL": "117",
    "univRating": "4",
    "SOP": "4.5",
    "LOR": "5",
    "CGPA": "9.42",
    "Research": "1",
    "admit": "0.94"
  },
  {
    "sn": {"": "216"},
    "GRE": "330",
    "TOEFL": "116",
    "univRating": "5",
    "SOP": "5",
    "LOR": "4.5",
    "CGPA": "9.36",
    "Research": "1",
    "admit": "0.93"
  },
  {
    "sn": {"": "217"},
    "GRE": "322",
    "TOEFL": "112",
    "univRating": "4",
    "SOP": "4.5",
    "LOR": "4.5",
    "CGPA": "9.26",
    "Research": "1",
    "admit": "0.91"
  },
  {
    "sn": {"": "218"},
    "GRE": "321",
    "TOEFL": "109",
    "univRating": "4",
    "SOP": "4",
    "LOR": "4",
    "CGPA": "9.13",
    "Research": "1",
    "admit": "0.85"
  },
  {
    "sn": {"": "219"},
    "GRE": "324",
    "TOEFL": "110",
    "univRating": "4",
    "SOP": "3",
    "LOR": "3.5",
    "CGPA": "8.97",
    "Research": "1",
    "admit": "0.84"
  },
  {
    "sn": {"": "220"},
    "GRE": "312",
    "TOEFL": "104",
    "univRating": "3",
    "SOP": "3.5",
    "LOR": "3.5",
    "CGPA": "8.42",
    "Research": "0",
    "admit": "0.74"
  },
  {
    "sn": {"": "221"},
    "GRE": "313",
    "TOEFL": "103",
    "univRating": "3",
    "SOP": "4",
    "LOR": "4",
    "CGPA": "8.75",
    "Research": "0",
    "admit": "0.76"
  },
  {
    "sn": {"": "222"},
    "GRE": "316",
    "TOEFL": "110",
    "univRating": "3",
    "SOP": "3.5",
    "LOR": "4",
    "CGPA": "8.56",
    "Research": "0",
    "admit": "0.75"
  },
  {
    "sn": {"": "223"},
    "GRE": "324",
    "TOEFL": "113",
    "univRating": "4",
    "SOP": "4.5",
    "LOR": "4",
    "CGPA": "8.79",
    "Research": "0",
    "admit": "0.76"
  },
  {
    "sn": {"": "224"},
    "GRE": "308",
    "TOEFL": "109",
    "univRating": "2",
    "SOP": "3",
    "LOR": "4",
    "CGPA": "8.45",
    "Research": "0",
    "admit": "0.71"
  },
  {
    "sn": {"": "225"},
    "GRE": "305",
    "TOEFL": "105",
    "univRating": "2",
    "SOP": "3",
    "LOR": "2",
    "CGPA": "8.23",
    "Research": "0",
    "admit": "0.67"
  },
  {
    "sn": {"": "226"},
    "GRE": "296",
    "TOEFL": "99",
    "univRating": "2",
    "SOP": "2.5",
    "LOR": "2.5",
    "CGPA": "8.03",
    "Research": "0",
    "admit": "0.61"
  },
  {
    "sn": {"": "227"},
    "GRE": "306",
    "TOEFL": "110",
    "univRating": "2",
    "SOP": "3.5",
    "LOR": "4",
    "CGPA": "8.45",
    "Research": "0",
    "admit": "0.63"
  },
  {
    "sn": {"": "228"},
    "GRE": "312",
    "TOEFL": "110",
    "univRating": "2",
    "SOP": "3.5",
    "LOR": "3",
    "CGPA": "8.53",
    "Research": "0",
    "admit": "0.64"
  },
  {
    "sn": {"": "229"},
    "GRE": "318",
    "TOEFL": "112",
    "univRating": "3",
    "SOP": "4",
    "LOR": "3.5",
    "CGPA": "8.67",
    "Research": "0",
    "admit": "0.71"
  },
  {
    "sn": {"": "230"},
    "GRE": "324",
    "TOEFL": "111",
    "univRating": "4",
    "SOP": "3",
    "LOR": "3",
    "CGPA": "9.01",
    "Research": "1",
    "admit": "0.82"
  },
  {
    "sn": {"": "231"},
    "GRE": "313",
    "TOEFL": "104",
    "univRating": "3",
    "SOP": "4",
    "LOR": "4.5",
    "CGPA": "8.65",
    "Research": "0",
    "admit": "0.73"
  },
  {
    "sn": {"": "232"},
    "GRE": "319",
    "TOEFL": "106",
    "univRating": "3",
    "SOP": "3.5",
    "LOR": "2.5",
    "CGPA": "8.33",
    "Research": "1",
    "admit": "0.74"
  },
  {
    "sn": {"": "233"},
    "GRE": "312",
    "TOEFL": "107",
    "univRating": "2",
    "SOP": "2.5",
    "LOR": "3.5",
    "CGPA": "8.27",
    "Research": "0",
    "admit": "0.69"
  },
  {
    "sn": {"": "234"},
    "GRE": "304",
    "TOEFL": "100",
    "univRating": "2",
    "SOP": "2.5",
    "LOR": "3.5",
    "CGPA": "8.07",
    "Research": "0",
    "admit": "0.64"
  },
  {
    "sn": {"": "235"},
    "GRE": "330",
    "TOEFL": "113",
    "univRating": "5",
    "SOP": "5",
    "LOR": "4",
    "CGPA": "9.31",
    "Research": "1",
    "admit": "0.91"
  },
  {
    "sn": {"": "236"},
    "GRE": "326",
    "TOEFL": "111",
    "univRating": "5",
    "SOP": "4.5",
    "LOR": "4",
    "CGPA": "9.23",
    "Research": "1",
    "admit": "0.88"
  },
  {
    "sn": {"": "237"},
    "GRE": "325",
    "TOEFL": "112",
    "univRating": "4",
    "SOP": "4",
    "LOR": "4.5",
    "CGPA": "9.17",
    "Research": "1",
    "admit": "0.85"
  },
  {
    "sn": {"": "238"},
    "GRE": "329",
    "TOEFL": "114",
    "univRating": "5",
    "SOP": "4.5",
    "LOR": "5",
    "CGPA": "9.19",
    "Research": "1",
    "admit": "0.86"
  },
  {
    "sn": {"": "239"},
    "GRE": "310",
    "TOEFL": "104",
    "univRating": "3",
    "SOP": "2",
    "LOR": "3.5",
    "CGPA": "8.37",
    "Research": "0",
    "admit": "0.7"
  },
  {
    "sn": {"": "240"},
    "GRE": "299",
    "TOEFL": "100",
    "univRating": "1",
    "SOP": "1.5",
    "LOR": "2",
    "CGPA": "7.89",
    "Research": "0",
    "admit": "0.59"
  },
  {
    "sn": {"": "241"},
    "GRE": "296",
    "TOEFL": "101",
    "univRating": "1",
    "SOP": "2.5",
    "LOR": "3",
    "CGPA": "7.68",
    "Research": "0",
    "admit": "0.6"
  },
  {
    "sn": {"": "242"},
    "GRE": "317",
    "TOEFL": "103",
    "univRating": "2",
    "SOP": "2.5",
    "LOR": "2",
    "CGPA": "8.15",
    "Research": "0",
    "admit": "0.65"
  },
  {
    "sn": {"": "243"},
    "GRE": "324",
    "TOEFL": "115",
    "univRating": "3",
    "SOP": "3.5",
    "LOR": "3",
    "CGPA": "8.76",
    "Research": "1",
    "admit": "0.7"
  },
  {
    "sn": {"": "244"},
    "GRE": "325",
    "TOEFL": "114",
    "univRating": "3",
    "SOP": "3.5",
    "LOR": "3",
    "CGPA": "9.04",
    "Research": "1",
    "admit": "0.76"
  },
  {
    "sn": {"": "245"},
    "GRE": "314",
    "TOEFL": "107",
    "univRating": "2",
    "SOP": "2.5",
    "LOR": "4",
    "CGPA": "8.56",
    "Research": "0",
    "admit": "0.63"
  },
  {
    "sn": {"": "246"},
    "GRE": "328",
    "TOEFL": "110",
    "univRating": "4",
    "SOP": "4",
    "LOR": "2.5",
    "CGPA": "9.02",
    "Research": "1",
    "admit": "0.81"
  },
  {
    "sn": {"": "247"},
    "GRE": "316",
    "TOEFL": "105",
    "univRating": "3",
    "SOP": "3",
    "LOR": "3.5",
    "CGPA": "8.73",
    "Research": "0",
    "admit": "0.72"
  },
  {
    "sn": {"": "248"},
    "GRE": "311",
    "TOEFL": "104",
    "univRating": "2",
    "SOP": "2.5",
    "LOR": "3.5",
    "CGPA": "8.48",
    "Research": "0",
    "admit": "0.71"
  },
  {
    "sn": {"": "249"},
    "GRE": "324",
    "TOEFL": "110",
    "univRating": "3",
    "SOP": "3.5",
    "LOR": "4",
    "CGPA": "8.87",
    "Research": "1",
    "admit": "0.8"
  },
  {
    "sn": {"": "250"},
    "GRE": "321",
    "TOEFL": "111",
    "univRating": "3",
    "SOP": "3.5",
    "LOR": "4",
    "CGPA": "8.83",
    "Research": "1",
    "admit": "0.77"
  },
  {
    "sn": {"": "251"},
    "GRE": "320",
    "TOEFL": "104",
    "univRating": "3",
    "SOP": "3",
    "LOR": "2.5",
    "CGPA": "8.57",
    "Research": "1",
    "admit": "0.74"
  },
  {
    "sn": {"": "252"},
    "GRE": "316",
    "TOEFL": "99",
    "univRating": "2",
    "SOP": "2.5",
    "LOR": "3",
    "CGPA": "9",
    "Research": "0",
    "admit": "0.7"
  },
  {
    "sn": {"": "253"},
    "GRE": "318",
    "TOEFL": "100",
    "univRating": "2",
    "SOP": "2.5",
    "LOR": "3.5",
    "CGPA": "8.54",
    "Research": "1",
    "admit": "0.71"
  },
  {
    "sn": {"": "254"},
    "GRE": "335",
    "TOEFL": "115",
    "univRating": "4",
    "SOP": "4.5",
    "LOR": "4.5",
    "CGPA": "9.68",
    "Research": "1",
    "admit": "0.93"
  },
  {
    "sn": {"": "255"},
    "GRE": "321",
    "TOEFL": "114",
    "univRating": "4",
    "SOP": "4",
    "LOR": "5",
    "CGPA": "9.12",
    "Research": "0",
    "admit": "0.85"
  },
  {
    "sn": {"": "256"},
    "GRE": "307",
    "TOEFL": "110",
    "univRating": "4",
    "SOP": "4",
    "LOR": "4.5",
    "CGPA": "8.37",
    "Research": "0",
    "admit": "0.79"
  },
  {
    "sn": {"": "257"},
    "GRE": "309",
    "TOEFL": "99",
    "univRating": "3",
    "SOP": "4",
    "LOR": "4",
    "CGPA": "8.56",
    "Research": "0",
    "admit": "0.76"
  },
  {
    "sn": {"": "258"},
    "GRE": "324",
    "TOEFL": "100",
    "univRating": "3",
    "SOP": "4",
    "LOR": "5",
    "CGPA": "8.64",
    "Research": "1",
    "admit": "0.78"
  },
  {
    "sn": {"": "259"},
    "GRE": "326",
    "TOEFL": "102",
    "univRating": "4",
    "SOP": "5",
    "LOR": "5",
    "CGPA": "8.76",
    "Research": "1",
    "admit": "0.77"
  },
  {
    "sn": {"": "260"},
    "GRE": "331",
    "TOEFL": "119",
    "univRating": "4",
    "SOP": "5",
    "LOR": "4.5",
    "CGPA": "9.34",
    "Research": "1",
    "admit": "0.9"
  },
  {
    "sn": {"": "261"},
    "GRE": "327",
    "TOEFL": "108",
    "univRating": "5",
    "SOP": "5",
    "LOR": "3.5",
    "CGPA": "9.13",
    "Research": "1",
    "admit": "0.87"
  },
  {
    "sn": {"": "262"},
    "GRE": "312",
    "TOEFL": "104",
    "univRating": "3",
    "SOP": "3.5",
    "LOR": "4",
    "CGPA": "8.09",
    "Research": "0",
    "admit": "0.71"
  },
  {
    "sn": {"": "263"},
    "GRE": "308",
    "TOEFL": "103",
    "univRating": "2",
    "SOP": "2.5",
    "LOR": "4",
    "CGPA": "8.36",
    "Research": "1",
    "admit": "0.7"
  },
  {
    "sn": {"": "264"},
    "GRE": "324",
    "TOEFL": "111",
    "univRating": "3",
    "SOP": "2.5",
    "LOR": "1.5",
    "CGPA": "8.79",
    "Research": "1",
    "admit": "0.7"
  },
  {
    "sn": {"": "265"},
    "GRE": "325",
    "TOEFL": "110",
    "univRating": "2",
    "SOP": "3",
    "LOR": "2.5",
    "CGPA": "8.76",
    "Research": "1",
    "admit": "0.75"
  },
  {
    "sn": {"": "266"},
    "GRE": "313",
    "TOEFL": "102",
    "univRating": "3",
    "SOP": "2.5",
    "LOR": "2.5",
    "CGPA": "8.68",
    "Research": "0",
    "admit": "0.71"
  },
  {
    "sn": {"": "267"},
    "GRE": "312",
    "TOEFL": "105",
    "univRating": "2",
    "SOP": "2",
    "LOR": "2.5",
    "CGPA": "8.45",
    "Research": "0",
    "admit": "0.72"
  },
  {
    "sn": {"": "268"},
    "GRE": "314",
    "TOEFL": "107",
    "univRating": "3",
    "SOP": "3",
    "LOR": "3.5",
    "CGPA": "8.17",
    "Research": "1",
    "admit": "0.73"
  },
  {
    "sn": {"": "269"},
    "GRE": "327",
    "TOEFL": "113",
    "univRating": "4",
    "SOP": "4.5",
    "LOR": "5",
    "CGPA": "9.14",
    "Research": "0",
    "admit": "0.83"
  },
  {
    "sn": {"": "270"},
    "GRE": "308",
    "TOEFL": "108",
    "univRating": "4",
    "SOP": "4.5",
    "LOR": "5",
    "CGPA": "8.34",
    "Research": "0",
    "admit": "0.77"
  },
  {
    "sn": {"": "271"},
    "GRE": "306",
    "TOEFL": "105",
    "univRating": "2",
    "SOP": "2.5",
    "LOR": "3",
    "CGPA": "8.22",
    "Research": "1",
    "admit": "0.72"
  },
  {
    "sn": {"": "272"},
    "GRE": "299",
    "TOEFL": "96",
    "univRating": "2",
    "SOP": "1.5",
    "LOR": "2",
    "CGPA": "7.86",
    "Research": "0",
    "admit": "0.54"
  },
  {
    "sn": {"": "273"},
    "GRE": "294",
    "TOEFL": "95",
    "univRating": "1",
    "SOP": "1.5",
    "LOR": "1.5",
    "CGPA": "7.64",
    "Research": "0",
    "admit": "0.49"
  },
  {
    "sn": {"": "274"},
    "GRE": "312",
    "TOEFL": "99",
    "univRating": "1",
    "SOP": "1",
    "LOR": "1.5",
    "CGPA": "8.01",
    "Research": "1",
    "admit": "0.52"
  },
  {
    "sn": {"": "275"},
    "GRE": "315",
    "TOEFL": "100",
    "univRating": "1",
    "SOP": "2",
    "LOR": "2.5",
    "CGPA": "7.95",
    "Research": "0",
    "admit": "0.58"
  },
  {
    "sn": {"": "276"},
    "GRE": "322",
    "TOEFL": "110",
    "univRating": "3",
    "SOP": "3.5",
    "LOR": "3",
    "CGPA": "8.96",
    "Research": "1",
    "admit": "0.78"
  },
  {
    "sn": {"": "277"},
    "GRE": "329",
    "TOEFL": "113",
    "univRating": "5",
    "SOP": "5",
    "LOR": "4.5",
    "CGPA": "9.45",
    "Research": "1",
    "admit": "0.89"
  },
  {
    "sn": {"": "278"},
    "GRE": "320",
    "TOEFL": "101",
    "univRating": "2",
    "SOP": "2.5",
    "LOR": "3",
    "CGPA": "8.62",
    "Research": "0",
    "admit": "0.7"
  },
  {
    "sn": {"": "279"},
    "GRE": "308",
    "TOEFL": "103",
    "univRating": "2",
    "SOP": "3",
    "LOR": "3.5",
    "CGPA": "8.49",
    "Research": "0",
    "admit": "0.66"
  },
  {
    "sn": {"": "280"},
    "GRE": "304",
    "TOEFL": "102",
    "univRating": "2",
    "SOP": "3",
    "LOR": "4",
    "CGPA": "8.73",
    "Research": "0",
    "admit": "0.67"
  },
  {
    "sn": {"": "281"},
    "GRE": "311",
    "TOEFL": "102",
    "univRating": "3",
    "SOP": "4.5",
    "LOR": "4",
    "CGPA": "8.64",
    "Research": "1",
    "admit": "0.68"
  },
  {
    "sn": {"": "282"},
    "GRE": "317",
    "TOEFL": "110",
    "univRating": "3",
    "SOP": "4",
    "LOR": "4.5",
    "CGPA": "9.11",
    "Research": "1",
    "admit": "0.8"
  },
  {
    "sn": {"": "283"},
    "GRE": "312",
    "TOEFL": "106",
    "univRating": "3",
    "SOP": "4",
    "LOR": "3.5",
    "CGPA": "8.79",
    "Research": "1",
    "admit": "0.81"
  },
  {
    "sn": {"": "284"},
    "GRE": "321",
    "TOEFL": "111",
    "univRating": "3",
    "SOP": "2.5",
    "LOR": "3",
    "CGPA": "8.9",
    "Research": "1",
    "admit": "0.8"
  },
  {
    "sn": {"": "285"},
    "GRE": "340",
    "TOEFL": "112",
    "univRating": "4",
    "SOP": "5",
    "LOR": "4.5",
    "CGPA": "9.66",
    "Research": "1",
    "admit": "0.94"
  },
  {
    "sn": {"": "286"},
    "GRE": "331",
    "TOEFL": "116",
    "univRating": "5",
    "SOP": "4",
    "LOR": "4",
    "CGPA": "9.26",
    "Research": "1",
    "admit": "0.93"
  },
  {
    "sn": {"": "287"},
    "GRE": "336",
    "TOEFL": "118",
    "univRating": "5",
    "SOP": "4.5",
    "LOR": "4",
    "CGPA": "9.19",
    "Research": "1",
    "admit": "0.92"
  },
  {
    "sn": {"": "288"},
    "GRE": "324",
    "TOEFL": "114",
    "univRating": "5",
    "SOP": "5",
    "LOR": "4.5",
    "CGPA": "9.08",
    "Research": "1",
    "admit": "0.89"
  },
  {
    "sn": {"": "289"},
    "GRE": "314",
    "TOEFL": "104",
    "univRating": "4",
    "SOP": "5",
    "LOR": "5",
    "CGPA": "9.02",
    "Research": "0",
    "admit": "0.82"
  },
  {
    "sn": {"": "290"},
    "GRE": "313",
    "TOEFL": "109",
    "univRating": "3",
    "SOP": "4",
    "LOR": "3.5",
    "CGPA": "9",
    "Research": "0",
    "admit": "0.79"
  },
  {
    "sn": {"": "291"},
    "GRE": "307",
    "TOEFL": "105",
    "univRating": "2",
    "SOP": "2.5",
    "LOR": "3",
    "CGPA": "7.65",
    "Research": "0",
    "admit": "0.58"
  },
  {
    "sn": {"": "292"},
    "GRE": "300",
    "TOEFL": "102",
    "univRating": "2",
    "SOP": "1.5",
    "LOR": "2",
    "CGPA": "7.87",
    "Research": "0",
    "admit": "0.56"
  },
  {
    "sn": {"": "293"},
    "GRE": "302",
    "TOEFL": "99",
    "univRating": "2",
    "SOP": "1",
    "LOR": "2",
    "CGPA": "7.97",
    "Research": "0",
    "admit": "0.56"
  },
  {
    "sn": {"": "294"},
    "GRE": "312",
    "TOEFL": "98",
    "univRating": "1",
    "SOP": "3.5",
    "LOR": "3",
    "CGPA": "8.18",
    "Research": "1",
    "admit": "0.64"
  },
  {
    "sn": {"": "295"},
    "GRE": "316",
    "TOEFL": "101",
    "univRating": "2",
    "SOP": "2.5",
    "LOR": "2",
    "CGPA": "8.32",
    "Research": "1",
    "admit": "0.61"
  },
  {
    "sn": {"": "296"},
    "GRE": "317",
    "TOEFL": "100",
    "univRating": "2",
    "SOP": "3",
    "LOR": "2.5",
    "CGPA": "8.57",
    "Research": "0",
    "admit": "0.68"
  },
  {
    "sn": {"": "297"},
    "GRE": "310",
    "TOEFL": "107",
    "univRating": "3",
    "SOP": "3.5",
    "LOR": "3.5",
    "CGPA": "8.67",
    "Research": "0",
    "admit": "0.76"
  },
  {
    "sn": {"": "298"},
    "GRE": "320",
    "TOEFL": "120",
    "univRating": "3",
    "SOP": "4",
    "LOR": "4.5",
    "CGPA": "9.11",
    "Research": "0",
    "admit": "0.86"
  },
  {
    "sn": {"": "299"},
    "GRE": "330",
    "TOEFL": "114",
    "univRating": "3",
    "SOP": "4.5",
    "LOR": "4.5",
    "CGPA": "9.24",
    "Research": "1",
    "admit": "0.9"
  },
  {
    "sn": {"": "300"},
    "GRE": "305",
    "TOEFL": "112",
    "univRating": "3",
    "SOP": "3",
    "LOR": "3.5",
    "CGPA": "8.65",
    "Research": "0",
    "admit": "0.71"
  },
  {
    "sn": {"": "301"},
    "GRE": "309",
    "TOEFL": "106",
    "univRating": "2",
    "SOP": "2.5",
    "LOR": "2.5",
    "CGPA": "8",
    "Research": "0",
    "admit": "0.62"
  },
  {
    "sn": {"": "302"},
    "GRE": "319",
    "TOEFL": "108",
    "univRating": "2",
    "SOP": "2.5",
    "LOR": "3",
    "CGPA": "8.76",
    "Research": "0",
    "admit": "0.66"
  },
  {
    "sn": {"": "303"},
    "GRE": "322",
    "TOEFL": "105",
    "univRating": "2",
    "SOP": "3",
    "LOR": "3",
    "CGPA": "8.45",
    "Research": "1",
    "admit": "0.65"
  },
  {
    "sn": {"": "304"},
    "GRE": "323",
    "TOEFL": "107",
    "univRating": "3",
    "SOP": "3.5",
    "LOR": "3.5",
    "CGPA": "8.55",
    "Research": "1",
    "admit": "0.73"
  },
  {
    "sn": {"": "305"},
    "GRE": "313",
    "TOEFL": "106",
    "univRating": "2",
    "SOP": "2.5",
    "LOR": "2",
    "CGPA": "8.43",
    "Research": "0",
    "admit": "0.62"
  },
  {
    "sn": {"": "306"},
    "GRE": "321",
    "TOEFL": "109",
    "univRating": "3",
    "SOP": "3.5",
    "LOR": "3.5",
    "CGPA": "8.8",
    "Research": "1",
    "admit": "0.74"
  },
  {
    "sn": {"": "307"},
    "GRE": "323",
    "TOEFL": "110",
    "univRating": "3",
    "SOP": "4",
    "LOR": "3.5",
    "CGPA": "9.1",
    "Research": "1",
    "admit": "0.79"
  },
  {
    "sn": {"": "308"},
    "GRE": "325",
    "TOEFL": "112",
    "univRating": "4",
    "SOP": "4",
    "LOR": "4",
    "CGPA": "9",
    "Research": "1",
    "admit": "0.8"
  },
  {
    "sn": {"": "309"},
    "GRE": "312",
    "TOEFL": "108",
    "univRating": "3",
    "SOP": "3.5",
    "LOR": "3",
    "CGPA": "8.53",
    "Research": "0",
    "admit": "0.69"
  },
  {
    "sn": {"": "310"},
    "GRE": "308",
    "TOEFL": "110",
    "univRating": "4",
    "SOP": "3.5",
    "LOR": "3",
    "CGPA": "8.6",
    "Research": "0",
    "admit": "0.7"
  },
  {
    "sn": {"": "311"},
    "GRE": "320",
    "TOEFL": "104",
    "univRating": "3",
    "SOP": "3",
    "LOR": "3.5",
    "CGPA": "8.74",
    "Research": "1",
    "admit": "0.76"
  },
  {
    "sn": {"": "312"},
    "GRE": "328",
    "TOEFL": "108",
    "univRating": "4",
    "SOP": "4.5",
    "LOR": "4",
    "CGPA": "9.18",
    "Research": "1",
    "admit": "0.84"
  },
  {
    "sn": {"": "313"},
    "GRE": "311",
    "TOEFL": "107",
    "univRating": "4",
    "SOP": "4.5",
    "LOR": "4.5",
    "CGPA": "9",
    "Research": "1",
    "admit": "0.78"
  },
  {
    "sn": {"": "314"},
    "GRE": "301",
    "TOEFL": "100",
    "univRating": "3",
    "SOP": "3.5",
    "LOR": "3",
    "CGPA": "8.04",
    "Research": "0",
    "admit": "0.67"
  },
  {
    "sn": {"": "315"},
    "GRE": "305",
    "TOEFL": "105",
    "univRating": "2",
    "SOP": "3",
    "LOR": "4",
    "CGPA": "8.13",
    "Research": "0",
    "admit": "0.66"
  },
  {
    "sn": {"": "316"},
    "GRE": "308",
    "TOEFL": "104",
    "univRating": "2",
    "SOP": "2.5",
    "LOR": "3",
    "CGPA": "8.07",
    "Research": "0",
    "admit": "0.65"
  },
  {
    "sn": {"": "317"},
    "GRE": "298",
    "TOEFL": "101",
    "univRating": "2",
    "SOP": "1.5",
    "LOR": "2",
    "CGPA": "7.86",
    "Research": "0",
    "admit": "0.54"
  },
  {
    "sn": {"": "318"},
    "GRE": "300",
    "TOEFL": "99",
    "univRating": "1",
    "SOP": "1",
    "LOR": "2.5",
    "CGPA": "8.01",
    "Research": "0",
    "admit": "0.58"
  },
  {
    "sn": {"": "319"},
    "GRE": "324",
    "TOEFL": "111",
    "univRating": "3",
    "SOP": "2.5",
    "LOR": "2",
    "CGPA": "8.8",
    "Research": "1",
    "admit": "0.79"
  },
  {
    "sn": {"": "320"},
    "GRE": "327",
    "TOEFL": "113",
    "univRating": "4",
    "SOP": "3.5",
    "LOR": "3",
    "CGPA": "8.69",
    "Research": "1",
    "admit": "0.8"
  },
  {
    "sn": {"": "321"},
    "GRE": "317",
    "TOEFL": "106",
    "univRating": "3",
    "SOP": "4",
    "LOR": "3.5",
    "CGPA": "8.5",
    "Research": "1",
    "admit": "0.75"
  },
  {
    "sn": {"": "322"},
    "GRE": "323",
    "TOEFL": "104",
    "univRating": "3",
    "SOP": "4",
    "LOR": "4",
    "CGPA": "8.44",
    "Research": "1",
    "admit": "0.73"
  },
  {
    "sn": {"": "323"},
    "GRE": "314",
    "TOEFL": "107",
    "univRating": "2",
    "SOP": "2.5",
    "LOR": "4",
    "CGPA": "8.27",
    "Research": "0",
    "admit": "0.72"
  },
  {
    "sn": {"": "324"},
    "GRE": "305",
    "TOEFL": "102",
    "univRating": "2",
    "SOP": "2",
    "LOR": "2.5",
    "CGPA": "8.18",
    "Research": "0",
    "admit": "0.62"
  },
  {
    "sn": {"": "325"},
    "GRE": "315",
    "TOEFL": "104",
    "univRating": "3",
    "SOP": "3",
    "LOR": "2.5",
    "CGPA": "8.33",
    "Research": "0",
    "admit": "0.67"
  },
  {
    "sn": {"": "326"},
    "GRE": "326",
    "TOEFL": "116",
    "univRating": "3",
    "SOP": "3.5",
    "LOR": "4",
    "CGPA": "9.14",
    "Research": "1",
    "admit": "0.81"
  },
  {
    "sn": {"": "327"},
    "GRE": "299",
    "TOEFL": "100",
    "univRating": "3",
    "SOP": "2",
    "LOR": "2",
    "CGPA": "8.02",
    "Research": "0",
    "admit": "0.63"
  },
  {
    "sn": {"": "328"},
    "GRE": "295",
    "TOEFL": "101",
    "univRating": "2",
    "SOP": "2.5",
    "LOR": "2",
    "CGPA": "7.86",
    "Research": "0",
    "admit": "0.69"
  },
  {
    "sn": {"": "329"},
    "GRE": "324",
    "TOEFL": "112",
    "univRating": "4",
    "SOP": "4",
    "LOR": "3.5",
    "CGPA": "8.77",
    "Research": "1",
    "admit": "0.8"
  },
  {
    "sn": {"": "330"},
    "GRE": "297",
    "TOEFL": "96",
    "univRating": "2",
    "SOP": "2.5",
    "LOR": "1.5",
    "CGPA": "7.89",
    "Research": "0",
    "admit": "0.43"
  },
  {
    "sn": {"": "331"},
    "GRE": "327",
    "TOEFL": "113",
    "univRating": "3",
    "SOP": "3.5",
    "LOR": "3",
    "CGPA": "8.66",
    "Research": "1",
    "admit": "0.8"
  },
  {
    "sn": {"": "332"},
    "GRE": "311",
    "TOEFL": "105",
    "univRating": "2",
    "SOP": "3",
    "LOR": "2",
    "CGPA": "8.12",
    "Research": "1",
    "admit": "0.73"
  },
  {
    "sn": {"": "333"},
    "GRE": "308",
    "TOEFL": "106",
    "univRating": "3",
    "SOP": "3.5",
    "LOR": "2.5",
    "CGPA": "8.21",
    "Research": "1",
    "admit": "0.75"
  },
  {
    "sn": {"": "334"},
    "GRE": "319",
    "TOEFL": "108",
    "univRating": "3",
    "SOP": "3",
    "LOR": "3.5",
    "CGPA": "8.54",
    "Research": "1",
    "admit": "0.71"
  },
  {
    "sn": {"": "335"},
    "GRE": "312",
    "TOEFL": "107",
    "univRating": "4",
    "SOP": "4.5",
    "LOR": "4",
    "CGPA": "8.65",
    "Research": "1",
    "admit": "0.73"
  },
  {
    "sn": {"": "336"},
    "GRE": "325",
    "TOEFL": "111",
    "univRating": "4",
    "SOP": "4",
    "LOR": "4.5",
    "CGPA": "9.11",
    "Research": "1",
    "admit": "0.83"
  },
  {
    "sn": {"": "337"},
    "GRE": "319",
    "TOEFL": "110",
    "univRating": "3",
    "SOP": "3",
    "LOR": "2.5",
    "CGPA": "8.79",
    "Research": "0",
    "admit": "0.72"
  },
  {
    "sn": {"": "338"},
    "GRE": "332",
    "TOEFL": "118",
    "univRating": "5",
    "SOP": "5",
    "LOR": "5",
    "CGPA": "9.47",
    "Research": "1",
    "admit": "0.94"
  },
  {
    "sn": {"": "339"},
    "GRE": "323",
    "TOEFL": "108",
    "univRating": "5",
    "SOP": "4",
    "LOR": "4",
    "CGPA": "8.74",
    "Research": "1",
    "admit": "0.81"
  },
  {
    "sn": {"": "340"},
    "GRE": "324",
    "TOEFL": "107",
    "univRating": "5",
    "SOP": "3.5",
    "LOR": "4",
    "CGPA": "8.66",
    "Research": "1",
    "admit": "0.81"
  },
  {
    "sn": {"": "341"},
    "GRE": "312",
    "TOEFL": "107",
    "univRating": "3",
    "SOP": "3",
    "LOR": "3",
    "CGPA": "8.46",
    "Research": "1",
    "admit": "0.75"
  },
  {
    "sn": {"": "342"},
    "GRE": "326",
    "TOEFL": "110",
    "univRating": "3",
    "SOP": "3.5",
    "LOR": "3.5",
    "CGPA": "8.76",
    "Research": "1",
    "admit": "0.79"
  },
  {
    "sn": {"": "343"},
    "GRE": "308",
    "TOEFL": "106",
    "univRating": "3",
    "SOP": "3",
    "LOR": "3",
    "CGPA": "8.24",
    "Research": "0",
    "admit": "0.58"
  },
  {
    "sn": {"": "344"},
    "GRE": "305",
    "TOEFL": "103",
    "univRating": "2",
    "SOP": "2.5",
    "LOR": "3.5",
    "CGPA": "8.13",
    "Research": "0",
    "admit": "0.59"
  },
  {
    "sn": {"": "345"},
    "GRE": "295",
    "TOEFL": "96",
    "univRating": "2",
    "SOP": "1.5",
    "LOR": "2",
    "CGPA": "7.34",
    "Research": "0",
    "admit": "0.47"
  },
  {
    "sn": {"": "346"},
    "GRE": "316",
    "TOEFL": "98",
    "univRating": "1",
    "SOP": "1.5",
    "LOR": "2",
    "CGPA": "7.43",
    "Research": "0",
    "admit": "0.49"
  },
  {
    "sn": {"": "347"},
    "GRE": "304",
    "TOEFL": "97",
    "univRating": "2",
    "SOP": "1.5",
    "LOR": "2",
    "CGPA": "7.64",
    "Research": "0",
    "admit": "0.47"
  },
  {
    "sn": {"": "348"},
    "GRE": "299",
    "TOEFL": "94",
    "univRating": "1",
    "SOP": "1",
    "LOR": "1",
    "CGPA": "7.34",
    "Research": "0",
    "admit": "0.42"
  },
  {
    "sn": {"": "349"},
    "GRE": "302",
    "TOEFL": "99",
    "univRating": "1",
    "SOP": "2",
    "LOR": "2",
    "CGPA": "7.25",
    "Research": "0",
    "admit": "0.57"
  },
  {
    "sn": {"": "350"},
    "GRE": "313",
    "TOEFL": "101",
    "univRating": "3",
    "SOP": "2.5",
    "LOR": "3",
    "CGPA": "8.04",
    "Research": "0",
    "admit": "0.62"
  },
  {
    "sn": {"": "351"},
    "GRE": "318",
    "TOEFL": "107",
    "univRating": "3",
    "SOP": "3",
    "LOR": "3.5",
    "CGPA": "8.27",
    "Research": "1",
    "admit": "0.74"
  },
  {
    "sn": {"": "352"},
    "GRE": "325",
    "TOEFL": "110",
    "univRating": "4",
    "SOP": "3.5",
    "LOR": "4",
    "CGPA": "8.67",
    "Research": "1",
    "admit": "0.73"
  },
  {
    "sn": {"": "353"},
    "GRE": "303",
    "TOEFL": "100",
    "univRating": "2",
    "SOP": "3",
    "LOR": "3.5",
    "CGPA": "8.06",
    "Research": "1",
    "admit": "0.64"
  },
  {
    "sn": {"": "354"},
    "GRE": "300",
    "TOEFL": "102",
    "univRating": "3",
    "SOP": "3.5",
    "LOR": "2.5",
    "CGPA": "8.17",
    "Research": "0",
    "admit": "0.63"
  },
  {
    "sn": {"": "355"},
    "GRE": "297",
    "TOEFL": "98",
    "univRating": "2",
    "SOP": "2.5",
    "LOR": "3",
    "CGPA": "7.67",
    "Research": "0",
    "admit": "0.59"
  },
  {
    "sn": {"": "356"},
    "GRE": "317",
    "TOEFL": "106",
    "univRating": "2",
    "SOP": "2",
    "LOR": "3.5",
    "CGPA": "8.12",
    "Research": "0",
    "admit": "0.73"
  },
  {
    "sn": {"": "357"},
    "GRE": "327",
    "TOEFL": "109",
    "univRating": "3",
    "SOP": "3.5",
    "LOR": "4",
    "CGPA": "8.77",
    "Research": "1",
    "admit": "0.79"
  },
  {
    "sn": {"": "358"},
    "GRE": "301",
    "TOEFL": "104",
    "univRating": "2",
    "SOP": "3.5",
    "LOR": "3.5",
    "CGPA": "7.89",
    "Research": "1",
    "admit": "0.68"
  },
  {
    "sn": {"": "359"},
    "GRE": "314",
    "TOEFL": "105",
    "univRating": "2",
    "SOP": "2.5",
    "LOR": "2",
    "CGPA": "7.64",
    "Research": "0",
    "admit": "0.7"
  },
  {
    "sn": {"": "360"},
    "GRE": "321",
    "TOEFL": "107",
    "univRating": "2",
    "SOP": "2",
    "LOR": "1.5",
    "CGPA": "8.44",
    "Research": "0",
    "admit": "0.81"
  },
  {
    "sn": {"": "361"},
    "GRE": "322",
    "TOEFL": "110",
    "univRating": "3",
    "SOP": "4",
    "LOR": "5",
    "CGPA": "8.64",
    "Research": "1",
    "admit": "0.85"
  },
  {
    "sn": {"": "362"},
    "GRE": "334",
    "TOEFL": "116",
    "univRating": "4",
    "SOP": "4",
    "LOR": "3.5",
    "CGPA": "9.54",
    "Research": "1",
    "admit": "0.93"
  },
  {
    "sn": {"": "363"},
    "GRE": "338",
    "TOEFL": "115",
    "univRating": "5",
    "SOP": "4.5",
    "LOR": "5",
    "CGPA": "9.23",
    "Research": "1",
    "admit": "0.91"
  },
  {
    "sn": {"": "364"},
    "GRE": "306",
    "TOEFL": "103",
    "univRating": "2",
    "SOP": "2.5",
    "LOR": "3",
    "CGPA": "8.36",
    "Research": "0",
    "admit": "0.69"
  },
  {
    "sn": {"": "365"},
    "GRE": "313",
    "TOEFL": "102",
    "univRating": "3",
    "SOP": "3.5",
    "LOR": "4",
    "CGPA": "8.9",
    "Research": "1",
    "admit": "0.77"
  },
  {
    "sn": {"": "366"},
    "GRE": "330",
    "TOEFL": "114",
    "univRating": "4",
    "SOP": "4.5",
    "LOR": "3",
    "CGPA": "9.17",
    "Research": "1",
    "admit": "0.86"
  },
  {
    "sn": {"": "367"},
    "GRE": "320",
    "TOEFL": "104",
    "univRating": "3",
    "SOP": "3.5",
    "LOR": "4.5",
    "CGPA": "8.34",
    "Research": "1",
    "admit": "0.74"
  },
  {
    "sn": {"": "368"},
    "GRE": "311",
    "TOEFL": "98",
    "univRating": "1",
    "SOP": "1",
    "LOR": "2.5",
    "CGPA": "7.46",
    "Research": "0",
    "admit": "0.57"
  },
  {
    "sn": {"": "369"},
    "GRE": "298",
    "TOEFL": "92",
    "univRating": "1",
    "SOP": "2",
    "LOR": "2",
    "CGPA": "7.88",
    "Research": "0",
    "admit": "0.51"
  },
  {
    "sn": {"": "370"},
    "GRE": "301",
    "TOEFL": "98",
    "univRating": "1",
    "SOP": "2",
    "LOR": "3",
    "CGPA": "8.03",
    "Research": "1",
    "admit": "0.67"
  },
  {
    "sn": {"": "371"},
    "GRE": "310",
    "TOEFL": "103",
    "univRating": "2",
    "SOP": "2.5",
    "LOR": "2.5",
    "CGPA": "8.24",
    "Research": "0",
    "admit": "0.72"
  },
  {
    "sn": {"": "372"},
    "GRE": "324",
    "TOEFL": "110",
    "univRating": "3",
    "SOP": "3.5",
    "LOR": "3",
    "CGPA": "9.22",
    "Research": "1",
    "admit": "0.89"
  },
  {
    "sn": {"": "373"},
    "GRE": "336",
    "TOEFL": "119",
    "univRating": "4",
    "SOP": "4.5",
    "LOR": "4",
    "CGPA": "9.62",
    "Research": "1",
    "admit": "0.95"
  },
  {
    "sn": {"": "374"},
    "GRE": "321",
    "TOEFL": "109",
    "univRating": "3",
    "SOP": "3",
    "LOR": "3",
    "CGPA": "8.54",
    "Research": "1",
    "admit": "0.79"
  },
  {
    "sn": {"": "375"},
    "GRE": "315",
    "TOEFL": "105",
    "univRating": "2",
    "SOP": "2",
    "LOR": "2.5",
    "CGPA": "7.65",
    "Research": "0",
    "admit": "0.39"
  },
  {
    "sn": {"": "376"},
    "GRE": "304",
    "TOEFL": "101",
    "univRating": "2",
    "SOP": "2",
    "LOR": "2.5",
    "CGPA": "7.66",
    "Research": "0",
    "admit": "0.38"
  },
  {
    "sn": {"": "377"},
    "GRE": "297",
    "TOEFL": "96",
    "univRating": "2",
    "SOP": "2.5",
    "LOR": "2",
    "CGPA": "7.43",
    "Research": "0",
    "admit": "0.34"
  },
  {
    "sn": {"": "378"},
    "GRE": "290",
    "TOEFL": "100",
    "univRating": "1",
    "SOP": "1.5",
    "LOR": "2",
    "CGPA": "7.56",
    "Research": "0",
    "admit": "0.47"
  },
  {
    "sn": {"": "379"},
    "GRE": "303",
    "TOEFL": "98",
    "univRating": "1",
    "SOP": "2",
    "LOR": "2.5",
    "CGPA": "7.65",
    "Research": "0",
    "admit": "0.56"
  },
  {
    "sn": {"": "380"},
    "GRE": "311",
    "TOEFL": "99",
    "univRating": "1",
    "SOP": "2.5",
    "LOR": "3",
    "CGPA": "8.43",
    "Research": "1",
    "admit": "0.71"
  },
  {
    "sn": {"": "381"},
    "GRE": "322",
    "TOEFL": "104",
    "univRating": "3",
    "SOP": "3.5",
    "LOR": "4",
    "CGPA": "8.84",
    "Research": "1",
    "admit": "0.78"
  },
  {
    "sn": {"": "382"},
    "GRE": "319",
    "TOEFL": "105",
    "univRating": "3",
    "SOP": "3",
    "LOR": "3.5",
    "CGPA": "8.67",
    "Research": "1",
    "admit": "0.73"
  },
  {
    "sn": {"": "383"},
    "GRE": "324",
    "TOEFL": "110",
    "univRating": "4",
    "SOP": "4.5",
    "LOR": "4",
    "CGPA": "9.15",
    "Research": "1",
    "admit": "0.82"
  },
  {
    "sn": {"": "384"},
    "GRE": "300",
    "TOEFL": "100",
    "univRating": "3",
    "SOP": "3",
    "LOR": "3.5",
    "CGPA": "8.26",
    "Research": "0",
    "admit": "0.62"
  },
  {
    "sn": {"": "385"},
    "GRE": "340",
    "TOEFL": "113",
    "univRating": "4",
    "SOP": "5",
    "LOR": "5",
    "CGPA": "9.74",
    "Research": "1",
    "admit": "0.96"
  },
  {
    "sn": {"": "386"},
    "GRE": "335",
    "TOEFL": "117",
    "univRating": "5",
    "SOP": "5",
    "LOR": "5",
    "CGPA": "9.82",
    "Research": "1",
    "admit": "0.96"
  },
  {
    "sn": {"": "387"},
    "GRE": "302",
    "TOEFL": "101",
    "univRating": "2",
    "SOP": "2.5",
    "LOR": "3.5",
    "CGPA": "7.96",
    "Research": "0",
    "admit": "0.46"
  },
  {
    "sn": {"": "388"},
    "GRE": "307",
    "TOEFL": "105",
    "univRating": "2",
    "SOP": "2",
    "LOR": "3.5",
    "CGPA": "8.1",
    "Research": "0",
    "admit": "0.53"
  },
  {
    "sn": {"": "389"},
    "GRE": "296",
    "TOEFL": "97",
    "univRating": "2",
    "SOP": "1.5",
    "LOR": "2",
    "CGPA": "7.8",
    "Research": "0",
    "admit": "0.49"
  },
  {
    "sn": {"": "390"},
    "GRE": "320",
    "TOEFL": "108",
    "univRating": "3",
    "SOP": "3.5",
    "LOR": "4",
    "CGPA": "8.44",
    "Research": "1",
    "admit": "0.76"
  },
  {
    "sn": {"": "391"},
    "GRE": "314",
    "TOEFL": "102",
    "univRating": "2",
    "SOP": "2",
    "LOR": "2.5",
    "CGPA": "8.24",
    "Research": "0",
    "admit": "0.64"
  },
  {
    "sn": {"": "392"},
    "GRE": "318",
    "TOEFL": "106",
    "univRating": "3",
    "SOP": "2",
    "LOR": "3",
    "CGPA": "8.65",
    "Research": "0",
    "admit": "0.71"
  },
  {
    "sn": {"": "393"},
    "GRE": "326",
    "TOEFL": "112",
    "univRating": "4",
    "SOP": "4",
    "LOR": "3.5",
    "CGPA": "9.12",
    "Research": "1",
    "admit": "0.84"
  },
  {
    "sn": {"": "394"},
    "GRE": "317",
    "TOEFL": "104",
    "univRating": "2",
    "SOP": "3",
    "LOR": "3",
    "CGPA": "8.76",
    "Research": "0",
    "admit": "0.77"
  },
  {
    "sn": {"": "395"},
    "GRE": "329",
    "TOEFL": "111",
    "univRating": "4",
    "SOP": "4.5",
    "LOR": "4",
    "CGPA": "9.23",
    "Research": "1",
    "admit": "0.89"
  },
  {
    "sn": {"": "396"},
    "GRE": "324",
    "TOEFL": "110",
    "univRating": "3",
    "SOP": "3.5",
    "LOR": "3.5",
    "CGPA": "9.04",
    "Research": "1",
    "admit": "0.82"
  },
  {
    "sn": {"": "397"},
    "GRE": "325",
    "TOEFL": "107",
    "univRating": "3",
    "SOP": "3",
    "LOR": "3.5",
    "CGPA": "9.11",
    "Research": "1",
    "admit": "0.84"
  },
  {
    "sn": {"": "398"},
    "GRE": "330",
    "TOEFL": "116",
    "univRating": "4",
    "SOP": "5",
    "LOR": "4.5",
    "CGPA": "9.45",
    "Research": "1",
    "admit": "0.91"
  },
  {
    "sn": {"": "399"},
    "GRE": "312",
    "TOEFL": "103",
    "univRating": "3",
    "SOP": "3.5",
    "LOR": "4",
    "CGPA": "8.78",
    "Research": "0",
    "admit": "0.67"
  },
  {
    "sn": {"": "400"},
    "GRE": "333",
    "TOEFL": "117",
    "univRating": "4",
    "SOP": "5",
    "LOR": "4",
    "CGPA": "9.66",
    "Research": "1",
    "admit": "0.95"
  }
]
